{
  "success": true,
  "simulation_type": "multi_golfer_single_runner",
  "orders": [
    {
      "order_id": "001",
      "golfer_group_id": 13,
      "golfer_id": "G13",
      "hole_num": 8,
      "order_time_s": 14768,
      "status": "processed",
      "total_completion_time_s": 761.6109539658246
    },
    {
      "order_id": "002",
      "golfer_group_id": 5,
      "golfer_id": "G5",
      "hole_num": 13,
      "order_time_s": 15685,
      "status": "processed",
      "total_completion_time_s": 1345.2248246671625
    },
    {
      "order_id": "003",
      "golfer_group_id": 10,
      "golfer_id": "G10",
      "hole_num": 11,
      "order_time_s": 16450,
      "status": "processed",
      "total_completion_time_s": 1785.7462320496415
    },
    {
      "order_id": "004",
      "golfer_group_id": 9,
      "golfer_id": "G9",
      "hole_num": 12,
      "order_time_s": 16613,
      "status": "processed",
      "total_completion_time_s": 2758.160355868775
    },
    {
      "order_id": "005",
      "golfer_group_id": 14,
      "golfer_id": "G14",
      "hole_num": 10,
      "order_time_s": 16811,
      "status": "processed",
      "total_completion_time_s": 3742.7816189957593
    },
    {
      "order_id": "006",
      "golfer_group_id": 7,
      "golfer_id": "G7",
      "hole_num": 14,
      "order_time_s": 17153,
      "status": "failed",
      "total_completion_time_s": 0.0
    },
    {
      "order_id": "007",
      "golfer_group_id": 4,
      "golfer_id": "G4",
      "hole_num": 16,
      "order_time_s": 17186,
      "status": "failed",
      "total_completion_time_s": 0.0
    },
    {
      "order_id": "008",
      "golfer_group_id": 15,
      "golfer_id": "G15",
      "hole_num": 10,
      "order_time_s": 17420,
      "status": "failed",
      "total_completion_time_s": 0.0
    },
    {
      "order_id": "009",
      "golfer_group_id": 24,
      "golfer_id": "G24",
      "hole_num": 4,
      "order_time_s": 17914,
      "status": "failed",
      "total_completion_time_s": 0.0
    },
    {
      "order_id": "010",
      "golfer_group_id": 4,
      "golfer_id": "G4",
      "hole_num": 17,
      "order_time_s": 18077,
      "status": "failed",
      "total_completion_time_s": 0.0
    },
    {
      "order_id": "011",
      "golfer_group_id": 8,
      "golfer_id": "G8",
      "hole_num": 16,
      "order_time_s": 18939,
      "status": "failed",
      "total_completion_time_s": 0.0
    },
    {
      "order_id": "012",
      "golfer_group_id": 29,
      "golfer_id": "G29",
      "hole_num": 2,
      "order_time_s": 19214,
      "status": "failed",
      "total_completion_time_s": 0.0
    },
    {
      "order_id": "013",
      "golfer_group_id": 19,
      "golfer_id": "G19",
      "hole_num": 9,
      "order_time_s": 19363,
      "status": "failed",
      "total_completion_time_s": 0.0
    },
    {
      "order_id": "014",
      "golfer_group_id": 24,
      "golfer_id": "G24",
      "hole_num": 7,
      "order_time_s": 20377,
      "status": "processed",
      "total_completion_time_s": 3842.4502057861755
    },
    {
      "order_id": "015",
      "golfer_group_id": 9,
      "golfer_id": "G9",
      "hole_num": 17,
      "order_time_s": 20548,
      "status": "failed",
      "total_completion_time_s": 0.0
    },
    {
      "order_id": "016",
      "golfer_group_id": 18,
      "golfer_id": "G18",
      "hole_num": 11,
      "order_time_s": 20772,
      "status": "failed",
      "total_completion_time_s": 0.0
    },
    {
      "order_id": "017",
      "golfer_group_id": 26,
      "golfer_id": "G26",
      "hole_num": 6,
      "order_time_s": 20967,
      "status": "failed",
      "total_completion_time_s": 0.0
    },
    {
      "order_id": "018",
      "golfer_group_id": 14,
      "golfer_id": "G14",
      "hole_num": 15,
      "order_time_s": 21151,
      "status": "failed",
      "total_completion_time_s": 0.0
    },
    {
      "order_id": "019",
      "golfer_group_id": 12,
      "golfer_id": "G12",
      "hole_num": 17,
      "order_time_s": 21570,
      "status": "failed",
      "total_completion_time_s": 0.0
    },
    {
      "order_id": "020",
      "golfer_group_id": 9,
      "golfer_id": "G9",
      "hole_num": 18,
      "order_time_s": 21588,
      "status": "failed",
      "total_completion_time_s": 0.0
    },
    {
      "order_id": "021",
      "golfer_group_id": 29,
      "golfer_id": "G29",
      "hole_num": 6,
      "order_time_s": 22224,
      "status": "failed",
      "total_completion_time_s": 0.0
    },
    {
      "order_id": "022",
      "golfer_group_id": 20,
      "golfer_id": "G20",
      "hole_num": 11,
      "order_time_s": 22336,
      "status": "failed",
      "total_completion_time_s": 0.0
    },
    {
      "order_id": "023",
      "golfer_group_id": 12,
      "golfer_id": "G12",
      "hole_num": 18,
      "order_time_s": 22470,
      "status": "failed",
      "total_completion_time_s": 0.0
    },
    {
      "order_id": "024",
      "golfer_group_id": 19,
      "golfer_id": "G19",
      "hole_num": 12,
      "order_time_s": 22587,
      "status": "failed",
      "total_completion_time_s": 0.0
    },
    {
      "order_id": "025",
      "golfer_group_id": 38,
      "golfer_id": "G38",
      "hole_num": 1,
      "order_time_s": 22763,
      "status": "failed",
      "total_completion_time_s": 0.0
    },
    {
      "order_id": "026",
      "golfer_group_id": 15,
      "golfer_id": "G15",
      "hole_num": 16,
      "order_time_s": 22833,
      "status": "failed",
      "total_completion_time_s": 0.0
    },
    {
      "order_id": "027",
      "golfer_group_id": 40,
      "golfer_id": "G40",
      "hole_num": 1,
      "order_time_s": 23948,
      "status": "processed",
      "total_completion_time_s": 3894.1117714185057
    },
    {
      "order_id": "028",
      "golfer_group_id": 28,
      "golfer_id": "G28",
      "hole_num": 9,
      "order_time_s": 24575,
      "status": "failed",
      "total_completion_time_s": 0.0
    },
    {
      "order_id": "029",
      "golfer_group_id": 30,
      "golfer_id": "G30",
      "hole_num": 8,
      "order_time_s": 24899,
      "status": "failed",
      "total_completion_time_s": 0.0
    },
    {
      "order_id": "030",
      "golfer_group_id": 42,
      "golfer_id": "G42",
      "hole_num": 2,
      "order_time_s": 25774,
      "status": "failed",
      "total_completion_time_s": 0.0
    },
    {
      "order_id": "031",
      "golfer_group_id": 32,
      "golfer_id": "G32",
      "hole_num": 9,
      "order_time_s": 26800,
      "status": "processed",
      "total_completion_time_s": 3665.7462320496415
    },
    {
      "order_id": "032",
      "golfer_group_id": 36,
      "golfer_id": "G36",
      "hole_num": 7,
      "order_time_s": 26875,
      "status": "failed",
      "total_completion_time_s": 0.0
    },
    {
      "order_id": "033",
      "golfer_group_id": 46,
      "golfer_id": "G46",
      "hole_num": 2,
      "order_time_s": 28438,
      "status": "processed",
      "total_completion_time_s": 3512.006204049656
    },
    {
      "order_id": "034",
      "golfer_group_id": 44,
      "golfer_id": "G44",
      "hole_num": 4,
      "order_time_s": 28733,
      "status": "failed",
      "total_completion_time_s": 0.0
    },
    {
      "order_id": "035",
      "golfer_group_id": 47,
      "golfer_id": "G47",
      "hole_num": 4,
      "order_time_s": 30193,
      "status": "processed",
      "total_completion_time_s": 3160.0808915313464
    },
    {
      "order_id": "036",
      "golfer_group_id": 52,
      "golfer_id": "G52",
      "hole_num": 1,
      "order_time_s": 30700,
      "status": "failed",
      "total_completion_time_s": 0.0
    },
    {
      "order_id": "037",
      "golfer_group_id": 29,
      "golfer_id": "G29",
      "hole_num": 18,
      "order_time_s": 31839,
      "status": "processed",
      "total_completion_time_s": 3307.86381039369
    },
    {
      "order_id": "038",
      "golfer_group_id": 49,
      "golfer_id": "G49",
      "hole_num": 6,
      "order_time_s": 33494,
      "status": "processed",
      "total_completion_time_s": 2645.1619461807495
    },
    {
      "order_id": "039",
      "golfer_group_id": 32,
      "golfer_id": "G32",
      "hole_num": 18,
      "order_time_s": 33567,
      "status": "processed",
      "total_completion_time_s": 3554.86381039369
    },
    {
      "order_id": "040",
      "golfer_group_id": 39,
      "golfer_id": "G39",
      "hole_num": 14,
      "order_time_s": 34549,
      "status": "processed",
      "total_completion_time_s": 3571.830134556709
    },
    {
      "order_id": "041",
      "golfer_group_id": 56,
      "golfer_id": "G56",
      "hole_num": 5,
      "order_time_s": 35629,
      "status": "processed",
      "total_completion_time_s": 3622.0316239951135
    },
    {
      "order_id": "042",
      "golfer_group_id": 35,
      "golfer_id": "G35",
      "hole_num": 18,
      "order_time_s": 35653,
      "status": "pending",
      "total_completion_time_s": 0.0
    },
    {
      "order_id": "043",
      "golfer_group_id": 46,
      "golfer_id": "G46",
      "hole_num": 11,
      "order_time_s": 36082,
      "status": "pending",
      "total_completion_time_s": 0.0
    },
    {
      "order_id": "044",
      "golfer_group_id": 50,
      "golfer_id": "G50",
      "hole_num": 9,
      "order_time_s": 36417,
      "status": "pending",
      "total_completion_time_s": 0.0
    },
    {
      "order_id": "045",
      "golfer_group_id": 44,
      "golfer_id": "G44",
      "hole_num": 13,
      "order_time_s": 36787,
      "status": "pending",
      "total_completion_time_s": 0.0
    },
    {
      "order_id": "046",
      "golfer_group_id": 46,
      "golfer_id": "G46",
      "hole_num": 12,
      "order_time_s": 36910,
      "status": "pending",
      "total_completion_time_s": 0.0
    },
    {
      "order_id": "047",
      "golfer_group_id": 59,
      "golfer_id": "G59",
      "hole_num": 2,
      "order_time_s": 38108,
      "status": "pending",
      "total_completion_time_s": 0.0
    },
    {
      "order_id": "048",
      "golfer_group_id": 61,
      "golfer_id": "G61",
      "hole_num": 1,
      "order_time_s": 38270,
      "status": "pending",
      "total_completion_time_s": 0.0
    },
    {
      "order_id": "049",
      "golfer_group_id": 53,
      "golfer_id": "G53",
      "hole_num": 10,
      "order_time_s": 38319,
      "status": "pending",
      "total_completion_time_s": 0.0
    },
    {
      "order_id": "050",
      "golfer_group_id": 41,
      "golfer_id": "G41",
      "hole_num": 18,
      "order_time_s": 38446,
      "status": "pending",
      "total_completion_time_s": 0.0
    }
  ],
  "orders_all": [
    {
      "order_id": "001",
      "golfer_group_id": 13,
      "golfer_id": "G13",
      "hole_num": 8,
      "order_time_s": 14768,
      "status": "processed",
      "total_completion_time_s": 761.6109539658246
    },
    {
      "order_id": "002",
      "golfer_group_id": 5,
      "golfer_id": "G5",
      "hole_num": 13,
      "order_time_s": 15685,
      "status": "processed",
      "total_completion_time_s": 1345.2248246671625
    },
    {
      "order_id": "003",
      "golfer_group_id": 10,
      "golfer_id": "G10",
      "hole_num": 11,
      "order_time_s": 16450,
      "status": "processed",
      "total_completion_time_s": 1785.7462320496415
    },
    {
      "order_id": "004",
      "golfer_group_id": 9,
      "golfer_id": "G9",
      "hole_num": 12,
      "order_time_s": 16613,
      "status": "processed",
      "total_completion_time_s": 2758.160355868775
    },
    {
      "order_id": "005",
      "golfer_group_id": 14,
      "golfer_id": "G14",
      "hole_num": 10,
      "order_time_s": 16811,
      "status": "processed",
      "total_completion_time_s": 3742.7816189957593
    },
    {
      "order_id": "006",
      "golfer_group_id": 7,
      "golfer_id": "G7",
      "hole_num": 14,
      "order_time_s": 17153,
      "status": "failed",
      "total_completion_time_s": 0.0
    },
    {
      "order_id": "007",
      "golfer_group_id": 4,
      "golfer_id": "G4",
      "hole_num": 16,
      "order_time_s": 17186,
      "status": "failed",
      "total_completion_time_s": 0.0
    },
    {
      "order_id": "008",
      "golfer_group_id": 15,
      "golfer_id": "G15",
      "hole_num": 10,
      "order_time_s": 17420,
      "status": "failed",
      "total_completion_time_s": 0.0
    },
    {
      "order_id": "009",
      "golfer_group_id": 24,
      "golfer_id": "G24",
      "hole_num": 4,
      "order_time_s": 17914,
      "status": "failed",
      "total_completion_time_s": 0.0
    },
    {
      "order_id": "010",
      "golfer_group_id": 4,
      "golfer_id": "G4",
      "hole_num": 17,
      "order_time_s": 18077,
      "status": "failed",
      "total_completion_time_s": 0.0
    },
    {
      "order_id": "011",
      "golfer_group_id": 8,
      "golfer_id": "G8",
      "hole_num": 16,
      "order_time_s": 18939,
      "status": "failed",
      "total_completion_time_s": 0.0
    },
    {
      "order_id": "012",
      "golfer_group_id": 29,
      "golfer_id": "G29",
      "hole_num": 2,
      "order_time_s": 19214,
      "status": "failed",
      "total_completion_time_s": 0.0
    },
    {
      "order_id": "013",
      "golfer_group_id": 19,
      "golfer_id": "G19",
      "hole_num": 9,
      "order_time_s": 19363,
      "status": "failed",
      "total_completion_time_s": 0.0
    },
    {
      "order_id": "014",
      "golfer_group_id": 24,
      "golfer_id": "G24",
      "hole_num": 7,
      "order_time_s": 20377,
      "status": "processed",
      "total_completion_time_s": 3842.4502057861755
    },
    {
      "order_id": "015",
      "golfer_group_id": 9,
      "golfer_id": "G9",
      "hole_num": 17,
      "order_time_s": 20548,
      "status": "failed",
      "total_completion_time_s": 0.0
    },
    {
      "order_id": "016",
      "golfer_group_id": 18,
      "golfer_id": "G18",
      "hole_num": 11,
      "order_time_s": 20772,
      "status": "failed",
      "total_completion_time_s": 0.0
    },
    {
      "order_id": "017",
      "golfer_group_id": 26,
      "golfer_id": "G26",
      "hole_num": 6,
      "order_time_s": 20967,
      "status": "failed",
      "total_completion_time_s": 0.0
    },
    {
      "order_id": "018",
      "golfer_group_id": 14,
      "golfer_id": "G14",
      "hole_num": 15,
      "order_time_s": 21151,
      "status": "failed",
      "total_completion_time_s": 0.0
    },
    {
      "order_id": "019",
      "golfer_group_id": 12,
      "golfer_id": "G12",
      "hole_num": 17,
      "order_time_s": 21570,
      "status": "failed",
      "total_completion_time_s": 0.0
    },
    {
      "order_id": "020",
      "golfer_group_id": 9,
      "golfer_id": "G9",
      "hole_num": 18,
      "order_time_s": 21588,
      "status": "failed",
      "total_completion_time_s": 0.0
    },
    {
      "order_id": "021",
      "golfer_group_id": 29,
      "golfer_id": "G29",
      "hole_num": 6,
      "order_time_s": 22224,
      "status": "failed",
      "total_completion_time_s": 0.0
    },
    {
      "order_id": "022",
      "golfer_group_id": 20,
      "golfer_id": "G20",
      "hole_num": 11,
      "order_time_s": 22336,
      "status": "failed",
      "total_completion_time_s": 0.0
    },
    {
      "order_id": "023",
      "golfer_group_id": 12,
      "golfer_id": "G12",
      "hole_num": 18,
      "order_time_s": 22470,
      "status": "failed",
      "total_completion_time_s": 0.0
    },
    {
      "order_id": "024",
      "golfer_group_id": 19,
      "golfer_id": "G19",
      "hole_num": 12,
      "order_time_s": 22587,
      "status": "failed",
      "total_completion_time_s": 0.0
    },
    {
      "order_id": "025",
      "golfer_group_id": 38,
      "golfer_id": "G38",
      "hole_num": 1,
      "order_time_s": 22763,
      "status": "failed",
      "total_completion_time_s": 0.0
    },
    {
      "order_id": "026",
      "golfer_group_id": 15,
      "golfer_id": "G15",
      "hole_num": 16,
      "order_time_s": 22833,
      "status": "failed",
      "total_completion_time_s": 0.0
    },
    {
      "order_id": "027",
      "golfer_group_id": 40,
      "golfer_id": "G40",
      "hole_num": 1,
      "order_time_s": 23948,
      "status": "processed",
      "total_completion_time_s": 3894.1117714185057
    },
    {
      "order_id": "028",
      "golfer_group_id": 28,
      "golfer_id": "G28",
      "hole_num": 9,
      "order_time_s": 24575,
      "status": "failed",
      "total_completion_time_s": 0.0
    },
    {
      "order_id": "029",
      "golfer_group_id": 30,
      "golfer_id": "G30",
      "hole_num": 8,
      "order_time_s": 24899,
      "status": "failed",
      "total_completion_time_s": 0.0
    },
    {
      "order_id": "030",
      "golfer_group_id": 42,
      "golfer_id": "G42",
      "hole_num": 2,
      "order_time_s": 25774,
      "status": "failed",
      "total_completion_time_s": 0.0
    },
    {
      "order_id": "031",
      "golfer_group_id": 32,
      "golfer_id": "G32",
      "hole_num": 9,
      "order_time_s": 26800,
      "status": "processed",
      "total_completion_time_s": 3665.7462320496415
    },
    {
      "order_id": "032",
      "golfer_group_id": 36,
      "golfer_id": "G36",
      "hole_num": 7,
      "order_time_s": 26875,
      "status": "failed",
      "total_completion_time_s": 0.0
    },
    {
      "order_id": "033",
      "golfer_group_id": 46,
      "golfer_id": "G46",
      "hole_num": 2,
      "order_time_s": 28438,
      "status": "processed",
      "total_completion_time_s": 3512.006204049656
    },
    {
      "order_id": "034",
      "golfer_group_id": 44,
      "golfer_id": "G44",
      "hole_num": 4,
      "order_time_s": 28733,
      "status": "failed",
      "total_completion_time_s": 0.0
    },
    {
      "order_id": "035",
      "golfer_group_id": 47,
      "golfer_id": "G47",
      "hole_num": 4,
      "order_time_s": 30193,
      "status": "processed",
      "total_completion_time_s": 3160.0808915313464
    },
    {
      "order_id": "036",
      "golfer_group_id": 52,
      "golfer_id": "G52",
      "hole_num": 1,
      "order_time_s": 30700,
      "status": "failed",
      "total_completion_time_s": 0.0
    },
    {
      "order_id": "037",
      "golfer_group_id": 29,
      "golfer_id": "G29",
      "hole_num": 18,
      "order_time_s": 31839,
      "status": "processed",
      "total_completion_time_s": 3307.86381039369
    },
    {
      "order_id": "038",
      "golfer_group_id": 49,
      "golfer_id": "G49",
      "hole_num": 6,
      "order_time_s": 33494,
      "status": "processed",
      "total_completion_time_s": 2645.1619461807495
    },
    {
      "order_id": "039",
      "golfer_group_id": 32,
      "golfer_id": "G32",
      "hole_num": 18,
      "order_time_s": 33567,
      "status": "processed",
      "total_completion_time_s": 3554.86381039369
    },
    {
      "order_id": "040",
      "golfer_group_id": 39,
      "golfer_id": "G39",
      "hole_num": 14,
      "order_time_s": 34549,
      "status": "processed",
      "total_completion_time_s": 3571.830134556709
    },
    {
      "order_id": "041",
      "golfer_group_id": 56,
      "golfer_id": "G56",
      "hole_num": 5,
      "order_time_s": 35629,
      "status": "processed",
      "total_completion_time_s": 3622.0316239951135
    },
    {
      "order_id": "042",
      "golfer_group_id": 35,
      "golfer_id": "G35",
      "hole_num": 18,
      "order_time_s": 35653,
      "status": "pending",
      "total_completion_time_s": 0.0
    },
    {
      "order_id": "043",
      "golfer_group_id": 46,
      "golfer_id": "G46",
      "hole_num": 11,
      "order_time_s": 36082,
      "status": "pending",
      "total_completion_time_s": 0.0
    },
    {
      "order_id": "044",
      "golfer_group_id": 50,
      "golfer_id": "G50",
      "hole_num": 9,
      "order_time_s": 36417,
      "status": "pending",
      "total_completion_time_s": 0.0
    },
    {
      "order_id": "045",
      "golfer_group_id": 44,
      "golfer_id": "G44",
      "hole_num": 13,
      "order_time_s": 36787,
      "status": "pending",
      "total_completion_time_s": 0.0
    },
    {
      "order_id": "046",
      "golfer_group_id": 46,
      "golfer_id": "G46",
      "hole_num": 12,
      "order_time_s": 36910,
      "status": "pending",
      "total_completion_time_s": 0.0
    },
    {
      "order_id": "047",
      "golfer_group_id": 59,
      "golfer_id": "G59",
      "hole_num": 2,
      "order_time_s": 38108,
      "status": "pending",
      "total_completion_time_s": 0.0
    },
    {
      "order_id": "048",
      "golfer_group_id": 61,
      "golfer_id": "G61",
      "hole_num": 1,
      "order_time_s": 38270,
      "status": "pending",
      "total_completion_time_s": 0.0
    },
    {
      "order_id": "049",
      "golfer_group_id": 53,
      "golfer_id": "G53",
      "hole_num": 10,
      "order_time_s": 38319,
      "status": "pending",
      "total_completion_time_s": 0.0
    },
    {
      "order_id": "050",
      "golfer_group_id": 41,
      "golfer_id": "G41",
      "hole_num": 18,
      "order_time_s": 38446,
      "status": "pending",
      "total_completion_time_s": 0.0
    }
  ],
  "delivery_stats": [
    {
      "order_id": "001",
      "golfer_group_id": 13,
      "hole_num": 9,
      "placed_hole_num": 8,
      "order_time_s": 14768,
      "queue_delay_s": 2,
      "prep_time_s": 600,
      "delivery_time_s": 159.6109539658246,
      "return_time_s": 714.2857142857143,
      "total_drive_time_s": 873.8966682515389,
      "delivery_distance_m": 893.8213422086158,
      "total_completion_time_s": 761.6109539658246,
      "delivered_at_time_s": 15529.610953965825,
      "runner_id": "runner_1",
      "order_node_idx": 84,
      "predicted_delivery_node_idx": 117,
      "actual_delivery_node_idx": 117,
      "trip_to_golfer": {
        "nodes": [
          "1",
          0,
          129,
          128,
          127,
          126,
          125,
          124,
          123,
          122,
          121,
          120,
          119,
          118,
          "117"
        ],
        "length_m": 446.91067110430794,
        "time_s": 159.61095396582428,
        "efficiency": null,
        "routing_type": "optimal"
      },
      "trip_back": {
        "nodes": [
          "117",
          118,
          119,
          120,
          121,
          122,
          123,
          124,
          125,
          126,
          127,
          128,
          129,
          0,
          "1"
        ],
        "length_m": 446.9106711043079,
        "time_s": 159.61095396582425,
        "efficiency": null,
        "routing_type": "optimal"
      },
      "predicted_delivery_location": [
        -84.5955799657709,
        34.04033604274497
      ]
    },
    {
      "order_id": "002",
      "golfer_group_id": 5,
      "hole_num": 15,
      "placed_hole_num": 13,
      "order_time_s": 15685,
      "queue_delay_s": 560,
      "prep_time_s": 600,
      "delivery_time_s": 185.22482466716247,
      "return_time_s": 285.7142857142857,
      "total_drive_time_s": 470.9391103814482,
      "delivery_distance_m": 1037.2590181361131,
      "total_completion_time_s": 1345.2248246671625,
      "delivered_at_time_s": 17030.224824667162,
      "runner_id": "runner_1",
      "order_node_idx": 144,
      "predicted_delivery_node_idx": 206,
      "actual_delivery_node_idx": 206,
      "trip_to_golfer": {
        "nodes": [
          "1",
          0,
          253,
          252,
          251,
          250,
          249,
          248,
          214,
          213,
          212,
          211,
          210,
          209,
          208,
          207,
          "206"
        ],
        "length_m": 518.6295090680566,
        "time_s": 185.22482466716306,
        "efficiency": null,
        "routing_type": "optimal"
      },
      "trip_back": {
        "nodes": [
          "206",
          207,
          208,
          209,
          210,
          211,
          212,
          213,
          214,
          248,
          249,
          250,
          251,
          252,
          253,
          0,
          "1"
        ],
        "length_m": 518.6295090680566,
        "time_s": 185.22482466716306,
        "efficiency": null,
        "routing_type": "optimal"
      },
      "predicted_delivery_location": [
        -84.5935619157102,
        34.03469779935424
      ]
    },
    {
      "order_id": "003",
      "golfer_group_id": 10,
      "hole_num": 13,
      "placed_hole_num": 11,
      "order_time_s": 16450,
      "queue_delay_s": 870,
      "prep_time_s": 600,
      "delivery_time_s": 315.74623204964155,
      "return_time_s": 428.5714285714286,
      "total_drive_time_s": 744.3176606210702,
      "delivery_distance_m": 1768.178899478001,
      "total_completion_time_s": 1785.7462320496415,
      "delivered_at_time_s": 18235.74623204964,
      "runner_id": "runner_1",
      "order_node_idx": 120,
      "predicted_delivery_node_idx": 186,
      "actual_delivery_node_idx": 186,
      "trip_to_golfer": {
        "nodes": [
          "1",
          0,
          253,
          252,
          251,
          250,
          249,
          248,
          247,
          246,
          245,
          244,
          243,
          242,
          241,
          240,
          239,
          238,
          237,
          236,
          235,
          234,
          233,
          232,
          190,
          189,
          188,
          187,
          "186"
        ],
        "length_m": 884.0894497390004,
        "time_s": 315.746232049643,
        "efficiency": null,
        "routing_type": "optimal"
      },
      "trip_back": {
        "nodes": [
          "186",
          187,
          188,
          189,
          190,
          232,
          233,
          234,
          235,
          236,
          237,
          238,
          239,
          240,
          241,
          242,
          243,
          244,
          245,
          246,
          247,
          248,
          249,
          250,
          251,
          252,
          253,
          0,
          "1"
        ],
        "length_m": 884.0894497390007,
        "time_s": 315.7462320496431,
        "efficiency": null,
        "routing_type": "optimal"
      },
      "predicted_delivery_location": [
        -84.59718719522306,
        34.03203886584515
      ]
    },
    {
      "order_id": "004",
      "golfer_group_id": 9,
      "hole_num": 15,
      "placed_hole_num": 12,
      "order_time_s": 16613,
      "queue_delay_s": 2052,
      "prep_time_s": 600,
      "delivery_time_s": 106.16035586877479,
      "return_time_s": 285.7142857142857,
      "total_drive_time_s": 391.8746415830605,
      "delivery_distance_m": 594.4979928651317,
      "total_completion_time_s": 2758.160355868775,
      "delivered_at_time_s": 19371.160355868775,
      "runner_id": "runner_1",
      "order_node_idx": 132,
      "predicted_delivery_node_idx": 213,
      "actual_delivery_node_idx": 213,
      "trip_to_golfer": {
        "nodes": [
          "1",
          0,
          253,
          252,
          251,
          250,
          249,
          248,
          214,
          "213"
        ],
        "length_m": 297.24899643256583,
        "time_s": 106.16035586877352,
        "efficiency": null,
        "routing_type": "optimal"
      },
      "trip_back": {
        "nodes": [
          "213",
          214,
          248,
          249,
          250,
          251,
          252,
          253,
          0,
          "1"
        ],
        "length_m": 297.2489964325658,
        "time_s": 106.1603558687735,
        "efficiency": null,
        "routing_type": "optimal"
      },
      "predicted_delivery_location": [
        -84.59419835476474,
        34.03652195996339
      ]
    },
    {
      "order_id": "005",
      "golfer_group_id": 14,
      "hole_num": 14,
      "placed_hole_num": 10,
      "order_time_s": 16811,
      "queue_delay_s": 2849,
      "prep_time_s": 600,
      "delivery_time_s": 293.78161899575935,
      "return_time_s": 357.14285714285717,
      "total_drive_time_s": 650.9244761386165,
      "delivery_distance_m": 1645.1770663762559,
      "total_completion_time_s": 3742.7816189957593,
      "delivered_at_time_s": 20553.78161899576,
      "runner_id": "runner_1",
      "order_node_idx": 108,
      "predicted_delivery_node_idx": 192,
      "actual_delivery_node_idx": 192,
      "trip_to_golfer": {
        "nodes": [
          "1",
          0,
          253,
          252,
          251,
          250,
          249,
          248,
          247,
          246,
          245,
          244,
          243,
          242,
          241,
          240,
          239,
          238,
          237,
          236,
          235,
          234,
          233,
          232,
          190,
          191,
          "192"
        ],
        "length_m": 822.5885331881279,
        "time_s": 293.78161899575997,
        "efficiency": null,
        "routing_type": "optimal"
      },
      "trip_back": {
        "nodes": [
          "192",
          191,
          190,
          232,
          233,
          234,
          235,
          236,
          237,
          238,
          239,
          240,
          241,
          242,
          243,
          244,
          245,
          246,
          247,
          248,
          249,
          250,
          251,
          252,
          253,
          0,
          "1"
        ],
        "length_m": 822.5885331881279,
        "time_s": 293.78161899575997,
        "efficiency": null,
        "routing_type": "optimal"
      },
      "predicted_delivery_location": [
        -84.59620296510113,
        34.03280841592644
      ]
    },
    {
      "order_id": "014",
      "golfer_group_id": 24,
      "hole_num": 11,
      "placed_hole_num": 7,
      "order_time_s": 20377,
      "queue_delay_s": 2958,
      "prep_time_s": 600,
      "delivery_time_s": 284.4502057861755,
      "return_time_s": 571.4285714285714,
      "total_drive_time_s": 855.878777214747,
      "delivery_distance_m": 1592.9211524025823,
      "total_completion_time_s": 3842.4502057861755,
      "delivered_at_time_s": 24219.450205786176,
      "runner_id": "runner_1",
      "order_node_idx": 72,
      "predicted_delivery_node_idx": 154,
      "actual_delivery_node_idx": 154,
      "trip_to_golfer": {
        "nodes": [
          "1",
          0,
          130,
          131,
          132,
          133,
          134,
          135,
          136,
          137,
          138,
          139,
          140,
          141,
          142,
          143,
          144,
          145,
          146,
          147,
          148,
          149,
          150,
          151,
          152,
          153,
          "154"
        ],
        "length_m": 796.4605762012911,
        "time_s": 284.45020578617545,
        "efficiency": null,
        "routing_type": "optimal"
      },
      "trip_back": {
        "nodes": [
          "154",
          153,
          152,
          151,
          150,
          149,
          148,
          147,
          146,
          145,
          144,
          143,
          142,
          141,
          140,
          139,
          138,
          137,
          136,
          135,
          134,
          133,
          132,
          131,
          130,
          0,
          "1"
        ],
        "length_m": 796.4605762012911,
        "time_s": 284.45020578617545,
        "efficiency": null,
        "routing_type": "optimal"
      },
      "predicted_delivery_location": [
        -84.59164551166387,
        34.03238190699464
      ]
    },
    {
      "order_id": "027",
      "golfer_group_id": 40,
      "hole_num": 6,
      "placed_hole_num": 1,
      "order_time_s": 23948,
      "queue_delay_s": 2692,
      "prep_time_s": 600,
      "delivery_time_s": 602.1117714185057,
      "return_time_s": 500.00000000000006,
      "total_drive_time_s": 1102.1117714185057,
      "delivery_distance_m": 3371.825919943637,
      "total_completion_time_s": 3894.1117714185057,
      "delivered_at_time_s": 27842.111771418506,
      "runner_id": "runner_1",
      "order_node_idx": 0,
      "predicted_delivery_node_idx": 71,
      "actual_delivery_node_idx": 71,
      "trip_to_golfer": {
        "nodes": [
          "1",
          0,
          129,
          128,
          127,
          126,
          125,
          124,
          123,
          122,
          121,
          120,
          119,
          118,
          117,
          116,
          115,
          114,
          113,
          106,
          105,
          104,
          103,
          102,
          101,
          100,
          99,
          98,
          97,
          96,
          95,
          94,
          93,
          92,
          91,
          90,
          89,
          88,
          87,
          86,
          85,
          84,
          83,
          82,
          81,
          80,
          79,
          78,
          77,
          76,
          75,
          74,
          73,
          72,
          "71"
        ],
        "length_m": 1685.9129599718187,
        "time_s": 602.1117714185067,
        "efficiency": null,
        "routing_type": "optimal"
      },
      "trip_back": {
        "nodes": [
          "71",
          72,
          73,
          74,
          75,
          76,
          77,
          78,
          79,
          80,
          81,
          82,
          83,
          84,
          85,
          86,
          87,
          88,
          89,
          90,
          91,
          92,
          93,
          94,
          95,
          96,
          97,
          98,
          99,
          100,
          101,
          102,
          103,
          104,
          105,
          106,
          113,
          114,
          115,
          116,
          117,
          118,
          119,
          120,
          121,
          122,
          123,
          124,
          125,
          126,
          127,
          128,
          129,
          0,
          "1"
        ],
        "length_m": 1685.9129599718183,
        "time_s": 602.1117714185066,
        "efficiency": null,
        "routing_type": "optimal"
      },
      "predicted_delivery_location": [
        -84.59423440112016,
        34.04386870793024
      ]
    },
    {
      "order_id": "031",
      "golfer_group_id": 32,
      "hole_num": 13,
      "placed_hole_num": 9,
      "order_time_s": 26800,
      "queue_delay_s": 2750,
      "prep_time_s": 600,
      "delivery_time_s": 315.74623204964155,
      "return_time_s": 428.5714285714286,
      "total_drive_time_s": 744.3176606210702,
      "delivery_distance_m": 1768.178899478001,
      "total_completion_time_s": 3665.7462320496415,
      "delivered_at_time_s": 30465.74623204964,
      "runner_id": "runner_1",
      "order_node_idx": 96,
      "predicted_delivery_node_idx": 186,
      "actual_delivery_node_idx": 186,
      "trip_to_golfer": {
        "nodes": [
          "1",
          0,
          253,
          252,
          251,
          250,
          249,
          248,
          247,
          246,
          245,
          244,
          243,
          242,
          241,
          240,
          239,
          238,
          237,
          236,
          235,
          234,
          233,
          232,
          190,
          189,
          188,
          187,
          "186"
        ],
        "length_m": 884.0894497390004,
        "time_s": 315.746232049643,
        "efficiency": null,
        "routing_type": "optimal"
      },
      "trip_back": {
        "nodes": [
          "186",
          187,
          188,
          189,
          190,
          232,
          233,
          234,
          235,
          236,
          237,
          238,
          239,
          240,
          241,
          242,
          243,
          244,
          245,
          246,
          247,
          248,
          249,
          250,
          251,
          252,
          253,
          0,
          "1"
        ],
        "length_m": 884.0894497390007,
        "time_s": 315.7462320496431,
        "efficiency": null,
        "routing_type": "optimal"
      },
      "predicted_delivery_location": [
        -84.59718719522306,
        34.03203886584515
      ]
    },
    {
      "order_id": "033",
      "golfer_group_id": 46,
      "hole_num": 6,
      "placed_hole_num": 2,
      "order_time_s": 28438,
      "queue_delay_s": 2462,
      "prep_time_s": 600,
      "delivery_time_s": 450.00620404965593,
      "return_time_s": 500.00000000000006,
      "total_drive_time_s": 950.0062040496559,
      "delivery_distance_m": 2520.034742678079,
      "total_completion_time_s": 3512.006204049656,
      "delivered_at_time_s": 31950.006204049656,
      "runner_id": "runner_1",
      "order_node_idx": 12,
      "predicted_delivery_node_idx": 85,
      "actual_delivery_node_idx": 85,
      "trip_to_golfer": {
        "nodes": [
          "1",
          0,
          129,
          128,
          127,
          126,
          125,
          124,
          123,
          122,
          121,
          120,
          119,
          118,
          117,
          116,
          115,
          114,
          113,
          106,
          105,
          104,
          103,
          102,
          101,
          100,
          99,
          98,
          97,
          96,
          95,
          94,
          93,
          92,
          91,
          90,
          89,
          88,
          87,
          86,
          "85"
        ],
        "length_m": 1260.0173713390395,
        "time_s": 450.006204049657,
        "efficiency": null,
        "routing_type": "optimal"
      },
      "trip_back": {
        "nodes": [
          "85",
          86,
          87,
          88,
          89,
          90,
          91,
          92,
          93,
          94,
          95,
          96,
          97,
          98,
          99,
          100,
          101,
          102,
          103,
          104,
          105,
          106,
          113,
          114,
          115,
          116,
          117,
          118,
          119,
          120,
          121,
          122,
          123,
          124,
          125,
          126,
          127,
          128,
          129,
          0,
          "1"
        ],
        "length_m": 1260.0173713390393,
        "time_s": 450.0062040496569,
        "efficiency": null,
        "routing_type": "optimal"
      },
      "predicted_delivery_location": [
        -84.59577850028815,
        34.04720717020048
      ]
    },
    {
      "order_id": "035",
      "golfer_group_id": 47,
      "hole_num": 7,
      "placed_hole_num": 4,
      "order_time_s": 30193,
      "queue_delay_s": 2267,
      "prep_time_s": 600,
      "delivery_time_s": 293.0808915313464,
      "return_time_s": 571.4285714285714,
      "total_drive_time_s": 864.5094629599179,
      "delivery_distance_m": 1641.2529925755348,
      "total_completion_time_s": 3160.0808915313464,
      "delivered_at_time_s": 33353.08089153135,
      "runner_id": "runner_1",
      "order_node_idx": 36,
      "predicted_delivery_node_idx": 99,
      "actual_delivery_node_idx": 99,
      "trip_to_golfer": {
        "nodes": [
          "1",
          0,
          129,
          128,
          127,
          126,
          125,
          124,
          123,
          122,
          121,
          120,
          119,
          118,
          117,
          116,
          115,
          114,
          113,
          106,
          105,
          104,
          103,
          102,
          101,
          100,
          "99"
        ],
        "length_m": 820.6264962877675,
        "time_s": 293.08089153134557,
        "efficiency": null,
        "routing_type": "optimal"
      },
      "trip_back": {
        "nodes": [
          "99",
          100,
          101,
          102,
          103,
          104,
          105,
          106,
          113,
          114,
          115,
          116,
          117,
          118,
          119,
          120,
          121,
          122,
          123,
          124,
          125,
          126,
          127,
          128,
          129,
          0,
          "1"
        ],
        "length_m": 820.6264962877673,
        "time_s": 293.08089153134546,
        "efficiency": null,
        "routing_type": "optimal"
      },
      "predicted_delivery_location": [
        -84.59554233748518,
        34.04359901271461
      ]
    },
    {
      "order_id": "037",
      "golfer_group_id": 29,
      "hole_num": -1,
      "placed_hole_num": 18,
      "order_time_s": 31839,
      "queue_delay_s": 2686,
      "prep_time_s": 600,
      "delivery_time_s": 21.863810393690073,
      "return_time_s": 357.14285714285717,
      "total_drive_time_s": 379.00666753654724,
      "delivery_distance_m": 122.43733820465803,
      "total_completion_time_s": 3307.86381039369,
      "delivered_at_time_s": 35146.86381039369,
      "runner_id": "runner_1",
      "order_node_idx": 204,
      "predicted_delivery_node_idx": 253,
      "actual_delivery_node_idx": 291,
      "trip_to_golfer": {
        "nodes": [
          "1",
          0,
          "253"
        ],
        "length_m": 61.21866910232902,
        "time_s": 21.863810393688937,
        "efficiency": null,
        "routing_type": "optimal"
      },
      "trip_back": {
        "nodes": [
          "253",
          0,
          "1"
        ],
        "length_m": 61.21866910232902,
        "time_s": 21.863810393688937,
        "efficiency": null,
        "routing_type": "optimal"
      },
      "predicted_delivery_location": [
        -84.59319770336151,
        34.03763997294976
      ]
    },
    {
      "order_id": "038",
      "golfer_group_id": 49,
      "hole_num": -1,
      "placed_hole_num": 6,
      "order_time_s": 33494,
      "queue_delay_s": 2011,
      "prep_time_s": 600,
      "delivery_time_s": 34.16194618074951,
      "return_time_s": 357.14285714285717,
      "total_drive_time_s": 391.3048033236067,
      "delivery_distance_m": 191.3068986121924,
      "total_completion_time_s": 2645.1619461807495,
      "delivered_at_time_s": 36139.16194618075,
      "runner_id": "runner_1",
      "order_node_idx": 60,
      "predicted_delivery_node_idx": 128,
      "actual_delivery_node_idx": 128,
      "trip_to_golfer": {
        "nodes": [
          "1",
          0,
          129,
          "128"
        ],
        "length_m": 95.6534493060962,
        "time_s": 34.16194618074865,
        "efficiency": null,
        "routing_type": "optimal"
      },
      "trip_back": {
        "nodes": [
          "128",
          129,
          0,
          "1"
        ],
        "length_m": 95.6534493060962,
        "time_s": 34.16194618074865,
        "efficiency": null,
        "routing_type": "optimal"
      },
      "predicted_delivery_location": [
        -84.59342515497553,
        34.03801670676076
      ]
    },
    {
      "order_id": "039",
      "golfer_group_id": 32,
      "hole_num": -1,
      "placed_hole_num": 18,
      "order_time_s": 33567,
      "queue_delay_s": 2933,
      "prep_time_s": 600,
      "delivery_time_s": 21.863810393690073,
      "return_time_s": 357.14285714285717,
      "total_drive_time_s": 379.00666753654724,
      "delivery_distance_m": 122.43733820465803,
      "total_completion_time_s": 3554.86381039369,
      "delivered_at_time_s": 37121.86381039369,
      "runner_id": "runner_1",
      "order_node_idx": 204,
      "predicted_delivery_node_idx": 253,
      "actual_delivery_node_idx": 297,
      "trip_to_golfer": {
        "nodes": [
          "1",
          0,
          "253"
        ],
        "length_m": 61.21866910232902,
        "time_s": 21.863810393688937,
        "efficiency": null,
        "routing_type": "optimal"
      },
      "trip_back": {
        "nodes": [
          "253",
          0,
          "1"
        ],
        "length_m": 61.21866910232902,
        "time_s": 21.863810393688937,
        "efficiency": null,
        "routing_type": "optimal"
      },
      "predicted_delivery_location": [
        -84.59319770336151,
        34.03763997294976
      ]
    },
    {
      "order_id": "040",
      "golfer_group_id": 39,
      "hole_num": -1,
      "placed_hole_num": 14,
      "order_time_s": 34549,
      "queue_delay_s": 2931,
      "prep_time_s": 600,
      "delivery_time_s": 40.8301345567088,
      "return_time_s": 357.14285714285717,
      "total_drive_time_s": 397.97299169956597,
      "delivery_distance_m": 228.648753517582,
      "total_completion_time_s": 3571.830134556709,
      "delivered_at_time_s": 38120.83013455671,
      "runner_id": "runner_1",
      "order_node_idx": 156,
      "predicted_delivery_node_idx": 251,
      "actual_delivery_node_idx": 251,
      "trip_to_golfer": {
        "nodes": [
          "1",
          0,
          253,
          252,
          "251"
        ],
        "length_m": 114.324376758791,
        "time_s": 40.83013455671107,
        "efficiency": null,
        "routing_type": "optimal"
      },
      "trip_back": {
        "nodes": [
          "251",
          252,
          253,
          0,
          "1"
        ],
        "length_m": 114.324376758791,
        "time_s": 40.83013455671107,
        "efficiency": null,
        "routing_type": "optimal"
      },
      "predicted_delivery_location": [
        -84.59373975192015,
        34.03752865476825
      ]
    },
    {
      "order_id": "041",
      "golfer_group_id": 56,
      "hole_num": 9,
      "placed_hole_num": 5,
      "order_time_s": 35629,
      "queue_delay_s": 2851,
      "prep_time_s": 600,
      "delivery_time_s": 171.03162399511348,
      "return_time_s": 714.2857142857143,
      "total_drive_time_s": 885.3173382808278,
      "delivery_distance_m": 957.7770943726407,
      "total_completion_time_s": 3622.0316239951135,
      "delivered_at_time_s": 39251.03162399511,
      "runner_id": "runner_1",
      "order_node_idx": 48,
      "predicted_delivery_node_idx": 116,
      "actual_delivery_node_idx": 117,
      "trip_to_golfer": {
        "nodes": [
          "1",
          0,
          129,
          128,
          127,
          126,
          125,
          124,
          123,
          122,
          121,
          120,
          119,
          118,
          117,
          "116"
        ],
        "length_m": 478.88854718632035,
        "time_s": 171.03162399511442,
        "efficiency": null,
        "routing_type": "optimal"
      },
      "trip_back": {
        "nodes": [
          "116",
          117,
          118,
          119,
          120,
          121,
          122,
          123,
          124,
          125,
          126,
          127,
          128,
          129,
          0,
          "1"
        ],
        "length_m": 478.8885471863203,
        "time_s": 171.03162399511442,
        "efficiency": null,
        "routing_type": "optimal"
      },
      "predicted_delivery_location": [
        -84.59562465722357,
        34.04062123227416
      ]
    }
  ],
  "failed_orders": [
    {
      "order_id": "006",
      "reason": "Not dispatched within 60 minutes"
    },
    {
      "order_id": "007",
      "reason": "Not dispatched within 60 minutes"
    },
    {
      "order_id": "008",
      "reason": "Not dispatched within 60 minutes"
    },
    {
      "order_id": "009",
      "reason": "Not dispatched within 60 minutes"
    },
    {
      "order_id": "010",
      "reason": "Not dispatched within 60 minutes"
    },
    {
      "order_id": "011",
      "reason": "Not dispatched within 60 minutes"
    },
    {
      "order_id": "012",
      "reason": "Not dispatched within 60 minutes"
    },
    {
      "order_id": "013",
      "reason": "Not dispatched within 60 minutes"
    },
    {
      "order_id": "015",
      "reason": "Not dispatched within 60 minutes"
    },
    {
      "order_id": "016",
      "reason": "Not dispatched within 60 minutes"
    },
    {
      "order_id": "017",
      "reason": "Not dispatched within 60 minutes"
    },
    {
      "order_id": "018",
      "reason": "Not dispatched within 60 minutes"
    },
    {
      "order_id": "019",
      "reason": "Not dispatched within 60 minutes"
    },
    {
      "order_id": "020",
      "reason": "Not dispatched within 60 minutes"
    },
    {
      "order_id": "021",
      "reason": "Not dispatched within 60 minutes"
    },
    {
      "order_id": "022",
      "reason": "Not dispatched within 60 minutes"
    },
    {
      "order_id": "023",
      "reason": "Not dispatched within 60 minutes"
    },
    {
      "order_id": "024",
      "reason": "Not dispatched within 60 minutes"
    },
    {
      "order_id": "025",
      "reason": "Not dispatched within 60 minutes"
    },
    {
      "order_id": "026",
      "reason": "Not dispatched within 60 minutes"
    },
    {
      "order_id": "028",
      "reason": "Not dispatched within 60 minutes"
    },
    {
      "order_id": "029",
      "reason": "Not dispatched within 60 minutes"
    },
    {
      "order_id": "030",
      "reason": "Not dispatched within 60 minutes"
    },
    {
      "order_id": "032",
      "reason": "Not dispatched within 60 minutes"
    },
    {
      "order_id": "034",
      "reason": "Not dispatched within 60 minutes"
    },
    {
      "order_id": "036",
      "reason": "Not dispatched within 60 minutes"
    }
  ],
  "activity_log": [
    {
      "timestamp_s": 0,
      "time_str": "07:00",
      "activity_type": "service_closed",
      "description": "runner_1 waiting 240 minutes until opening",
      "order_id": null,
      "location": "clubhouse",
      "runner_id": "runner_1"
    },
    {
      "timestamp_s": 14400,
      "time_str": "11:00",
      "activity_type": "service_opened",
      "description": "runner_1 started shift",
      "order_id": null,
      "location": "clubhouse",
      "runner_id": "runner_1"
    },
    {
      "timestamp_s": 14770,
      "time_str": "11:06",
      "activity_type": "order_assigned",
      "description": "Assigned Order 001 to runner_1",
      "order_id": "001",
      "location": "clubhouse",
      "runner_id": "runner_1"
    },
    {
      "timestamp_s": 14770,
      "time_str": "11:06",
      "activity_type": "prep_start",
      "description": "runner_1 started prep for Order 001 (Hole 8)",
      "order_id": "001",
      "location": "clubhouse",
      "runner_id": "runner_1"
    },
    {
      "timestamp_s": 15370,
      "time_str": "11:16",
      "activity_type": "prep_complete",
      "description": "runner_1 completed prep for Order 001",
      "order_id": "001",
      "location": "clubhouse",
      "runner_id": "runner_1"
    },
    {
      "timestamp_s": 15370,
      "time_str": "11:16",
      "activity_type": "delivery_start",
      "description": "runner_1 departing to Hole 9 (894m, 2.7 min)",
      "order_id": "001",
      "location": "clubhouse",
      "runner_id": "runner_1"
    },
    {
      "timestamp_s": 15529.610953965825,
      "time_str": "11:18",
      "activity_type": "delivery_complete",
      "description": "runner_1 delivered Order 001 to Hole 9 (Total completion: 12.7 min)",
      "order_id": "001",
      "location": "hole_9",
      "runner_id": "runner_1"
    },
    {
      "timestamp_s": 15529.610953965825,
      "time_str": "11:18",
      "activity_type": "returning",
      "description": "runner_1 returning to clubhouse from hole_9 (11.9 min)",
      "order_id": "001",
      "location": "hole_9",
      "runner_id": "runner_1"
    },
    {
      "timestamp_s": 16243.896668251538,
      "time_str": "11:30",
      "activity_type": "arrived_clubhouse",
      "description": "runner_1 arrived at clubhouse after delivering Order 001",
      "order_id": "001",
      "location": "clubhouse",
      "runner_id": "runner_1"
    },
    {
      "timestamp_s": 16245,
      "time_str": "11:30",
      "activity_type": "order_assigned",
      "description": "Assigned Order 002 to runner_1",
      "order_id": "002",
      "location": "clubhouse",
      "runner_id": "runner_1"
    },
    {
      "timestamp_s": 16245,
      "time_str": "11:30",
      "activity_type": "prep_start",
      "description": "runner_1 started prep for Order 002 (Hole 13)",
      "order_id": "002",
      "location": "clubhouse",
      "runner_id": "runner_1"
    },
    {
      "timestamp_s": 16845,
      "time_str": "11:40",
      "activity_type": "prep_complete",
      "description": "runner_1 completed prep for Order 002",
      "order_id": "002",
      "location": "clubhouse",
      "runner_id": "runner_1"
    },
    {
      "timestamp_s": 16845,
      "time_str": "11:40",
      "activity_type": "delivery_start",
      "description": "runner_1 departing to Hole 15 (1037m, 3.1 min)",
      "order_id": "002",
      "location": "clubhouse",
      "runner_id": "runner_1"
    },
    {
      "timestamp_s": 17030.224824667162,
      "time_str": "11:43",
      "activity_type": "delivery_complete",
      "description": "runner_1 delivered Order 002 to Hole 15 (Total completion: 22.4 min)",
      "order_id": "002",
      "location": "hole_15",
      "runner_id": "runner_1"
    },
    {
      "timestamp_s": 17030.224824667162,
      "time_str": "11:43",
      "activity_type": "returning",
      "description": "runner_1 returning to clubhouse from hole_15 (4.8 min)",
      "order_id": "002",
      "location": "hole_15",
      "runner_id": "runner_1"
    },
    {
      "timestamp_s": 17315.93911038145,
      "time_str": "11:48",
      "activity_type": "arrived_clubhouse",
      "description": "runner_1 arrived at clubhouse after delivering Order 002",
      "order_id": "002",
      "location": "clubhouse",
      "runner_id": "runner_1"
    },
    {
      "timestamp_s": 17320,
      "time_str": "11:48",
      "activity_type": "order_assigned",
      "description": "Assigned Order 003 to runner_1",
      "order_id": "003",
      "location": "clubhouse",
      "runner_id": "runner_1"
    },
    {
      "timestamp_s": 17320,
      "time_str": "11:48",
      "activity_type": "prep_start",
      "description": "runner_1 started prep for Order 003 (Hole 11)",
      "order_id": "003",
      "location": "clubhouse",
      "runner_id": "runner_1"
    },
    {
      "timestamp_s": 17920,
      "time_str": "11:58",
      "activity_type": "prep_complete",
      "description": "runner_1 completed prep for Order 003",
      "order_id": "003",
      "location": "clubhouse",
      "runner_id": "runner_1"
    },
    {
      "timestamp_s": 17920,
      "time_str": "11:58",
      "activity_type": "delivery_start",
      "description": "runner_1 departing to Hole 13 (1768m, 5.3 min)",
      "order_id": "003",
      "location": "clubhouse",
      "runner_id": "runner_1"
    },
    {
      "timestamp_s": 18235.74623204964,
      "time_str": "12:03",
      "activity_type": "delivery_complete",
      "description": "runner_1 delivered Order 003 to Hole 13 (Total completion: 29.8 min)",
      "order_id": "003",
      "location": "hole_13",
      "runner_id": "runner_1"
    },
    {
      "timestamp_s": 18235.74623204964,
      "time_str": "12:03",
      "activity_type": "returning",
      "description": "runner_1 returning to clubhouse from hole_13 (7.1 min)",
      "order_id": "003",
      "location": "hole_13",
      "runner_id": "runner_1"
    },
    {
      "timestamp_s": 18664.31766062107,
      "time_str": "12:11",
      "activity_type": "arrived_clubhouse",
      "description": "runner_1 arrived at clubhouse after delivering Order 003",
      "order_id": "003",
      "location": "clubhouse",
      "runner_id": "runner_1"
    },
    {
      "timestamp_s": 18665,
      "time_str": "12:11",
      "activity_type": "order_assigned",
      "description": "Assigned Order 004 to runner_1",
      "order_id": "004",
      "location": "clubhouse",
      "runner_id": "runner_1"
    },
    {
      "timestamp_s": 18665,
      "time_str": "12:11",
      "activity_type": "prep_start",
      "description": "runner_1 started prep for Order 004 (Hole 12)",
      "order_id": "004",
      "location": "clubhouse",
      "runner_id": "runner_1"
    },
    {
      "timestamp_s": 19265,
      "time_str": "12:21",
      "activity_type": "prep_complete",
      "description": "runner_1 completed prep for Order 004",
      "order_id": "004",
      "location": "clubhouse",
      "runner_id": "runner_1"
    },
    {
      "timestamp_s": 19265,
      "time_str": "12:21",
      "activity_type": "delivery_start",
      "description": "runner_1 departing to Hole 15 (594m, 1.8 min)",
      "order_id": "004",
      "location": "clubhouse",
      "runner_id": "runner_1"
    },
    {
      "timestamp_s": 19371.160355868775,
      "time_str": "12:22",
      "activity_type": "delivery_complete",
      "description": "runner_1 delivered Order 004 to Hole 15 (Total completion: 46.0 min)",
      "order_id": "004",
      "location": "hole_15",
      "runner_id": "runner_1"
    },
    {
      "timestamp_s": 19371.160355868775,
      "time_str": "12:22",
      "activity_type": "returning",
      "description": "runner_1 returning to clubhouse from hole_15 (4.8 min)",
      "order_id": "004",
      "location": "hole_15",
      "runner_id": "runner_1"
    },
    {
      "timestamp_s": 19656.87464158306,
      "time_str": "12:27",
      "activity_type": "arrived_clubhouse",
      "description": "runner_1 arrived at clubhouse after delivering Order 004",
      "order_id": "004",
      "location": "clubhouse",
      "runner_id": "runner_1"
    },
    {
      "timestamp_s": 19660,
      "time_str": "12:27",
      "activity_type": "order_assigned",
      "description": "Assigned Order 005 to runner_1",
      "order_id": "005",
      "location": "clubhouse",
      "runner_id": "runner_1"
    },
    {
      "timestamp_s": 19660,
      "time_str": "12:27",
      "activity_type": "prep_start",
      "description": "runner_1 started prep for Order 005 (Hole 10)",
      "order_id": "005",
      "location": "clubhouse",
      "runner_id": "runner_1"
    },
    {
      "timestamp_s": 20260,
      "time_str": "12:37",
      "activity_type": "prep_complete",
      "description": "runner_1 completed prep for Order 005",
      "order_id": "005",
      "location": "clubhouse",
      "runner_id": "runner_1"
    },
    {
      "timestamp_s": 20260,
      "time_str": "12:37",
      "activity_type": "delivery_start",
      "description": "runner_1 departing to Hole 14 (1645m, 4.9 min)",
      "order_id": "005",
      "location": "clubhouse",
      "runner_id": "runner_1"
    },
    {
      "timestamp_s": 20553.78161899576,
      "time_str": "12:42",
      "activity_type": "delivery_complete",
      "description": "runner_1 delivered Order 005 to Hole 14 (Total completion: 62.4 min)",
      "order_id": "005",
      "location": "hole_14",
      "runner_id": "runner_1"
    },
    {
      "timestamp_s": 20553.78161899576,
      "time_str": "12:42",
      "activity_type": "returning",
      "description": "runner_1 returning to clubhouse from hole_14 (6.0 min)",
      "order_id": "005",
      "location": "hole_14",
      "runner_id": "runner_1"
    },
    {
      "timestamp_s": 20910.924476138618,
      "time_str": "12:48",
      "activity_type": "arrived_clubhouse",
      "description": "runner_1 arrived at clubhouse after delivering Order 005",
      "order_id": "005",
      "location": "clubhouse",
      "runner_id": "runner_1"
    },
    {
      "timestamp_s": 20915,
      "time_str": "12:48",
      "activity_type": "order_assigned",
      "description": "Assigned Order 006 to runner_1",
      "order_id": "006",
      "location": "clubhouse",
      "runner_id": "runner_1"
    },
    {
      "timestamp_s": 20915,
      "time_str": "12:48",
      "activity_type": "order_failed_timeout",
      "description": "runner_1 received expired order 006; discarding",
      "order_id": "006",
      "location": "clubhouse",
      "runner_id": "runner_1"
    },
    {
      "timestamp_s": 20920,
      "time_str": "12:48",
      "activity_type": "order_assigned",
      "description": "Assigned Order 007 to runner_1",
      "order_id": "007",
      "location": "clubhouse",
      "runner_id": "runner_1"
    },
    {
      "timestamp_s": 20920,
      "time_str": "12:48",
      "activity_type": "order_failed_timeout",
      "description": "runner_1 received expired order 007; discarding",
      "order_id": "007",
      "location": "clubhouse",
      "runner_id": "runner_1"
    },
    {
      "timestamp_s": 20925,
      "time_str": "12:48",
      "activity_type": "order_assigned",
      "description": "Assigned Order 008 to runner_1",
      "order_id": "008",
      "location": "clubhouse",
      "runner_id": "runner_1"
    },
    {
      "timestamp_s": 20925,
      "time_str": "12:48",
      "activity_type": "prep_start",
      "description": "runner_1 started prep for Order 008 (Hole 10)",
      "order_id": "008",
      "location": "clubhouse",
      "runner_id": "runner_1"
    },
    {
      "timestamp_s": 21525,
      "time_str": "12:58",
      "activity_type": "prep_complete",
      "description": "runner_1 completed prep for Order 008",
      "order_id": "008",
      "location": "clubhouse",
      "runner_id": "runner_1"
    },
    {
      "timestamp_s": 21525,
      "time_str": "12:58",
      "activity_type": "order_failed_timeout",
      "description": "runner_1 exceeded timeout before departure for Order 008; discarding",
      "order_id": "008",
      "location": "clubhouse",
      "runner_id": "runner_1"
    },
    {
      "timestamp_s": 21525,
      "time_str": "12:58",
      "activity_type": "order_assigned",
      "description": "Assigned Order 009 to runner_1",
      "order_id": "009",
      "location": "clubhouse",
      "runner_id": "runner_1"
    },
    {
      "timestamp_s": 21525,
      "time_str": "12:58",
      "activity_type": "order_failed_timeout",
      "description": "runner_1 received expired order 009; discarding",
      "order_id": "009",
      "location": "clubhouse",
      "runner_id": "runner_1"
    },
    {
      "timestamp_s": 21530,
      "time_str": "12:58",
      "activity_type": "order_assigned",
      "description": "Assigned Order 010 to runner_1",
      "order_id": "010",
      "location": "clubhouse",
      "runner_id": "runner_1"
    },
    {
      "timestamp_s": 21530,
      "time_str": "12:58",
      "activity_type": "prep_start",
      "description": "runner_1 started prep for Order 010 (Hole 17)",
      "order_id": "010",
      "location": "clubhouse",
      "runner_id": "runner_1"
    },
    {
      "timestamp_s": 22130,
      "time_str": "13:08",
      "activity_type": "prep_complete",
      "description": "runner_1 completed prep for Order 010",
      "order_id": "010",
      "location": "clubhouse",
      "runner_id": "runner_1"
    },
    {
      "timestamp_s": 22130,
      "time_str": "13:08",
      "activity_type": "order_failed_timeout",
      "description": "runner_1 exceeded timeout before departure for Order 010; discarding",
      "order_id": "010",
      "location": "clubhouse",
      "runner_id": "runner_1"
    },
    {
      "timestamp_s": 22130,
      "time_str": "13:08",
      "activity_type": "order_assigned",
      "description": "Assigned Order 011 to runner_1",
      "order_id": "011",
      "location": "clubhouse",
      "runner_id": "runner_1"
    },
    {
      "timestamp_s": 22130,
      "time_str": "13:08",
      "activity_type": "prep_start",
      "description": "runner_1 started prep for Order 011 (Hole 16)",
      "order_id": "011",
      "location": "clubhouse",
      "runner_id": "runner_1"
    },
    {
      "timestamp_s": 22730,
      "time_str": "13:18",
      "activity_type": "prep_complete",
      "description": "runner_1 completed prep for Order 011",
      "order_id": "011",
      "location": "clubhouse",
      "runner_id": "runner_1"
    },
    {
      "timestamp_s": 22730,
      "time_str": "13:18",
      "activity_type": "order_failed_timeout",
      "description": "runner_1 exceeded timeout before departure for Order 011; discarding",
      "order_id": "011",
      "location": "clubhouse",
      "runner_id": "runner_1"
    },
    {
      "timestamp_s": 22730,
      "time_str": "13:18",
      "activity_type": "order_assigned",
      "description": "Assigned Order 012 to runner_1",
      "order_id": "012",
      "location": "clubhouse",
      "runner_id": "runner_1"
    },
    {
      "timestamp_s": 22730,
      "time_str": "13:18",
      "activity_type": "prep_start",
      "description": "runner_1 started prep for Order 012 (Hole 2)",
      "order_id": "012",
      "location": "clubhouse",
      "runner_id": "runner_1"
    },
    {
      "timestamp_s": 23330,
      "time_str": "13:28",
      "activity_type": "prep_complete",
      "description": "runner_1 completed prep for Order 012",
      "order_id": "012",
      "location": "clubhouse",
      "runner_id": "runner_1"
    },
    {
      "timestamp_s": 23330,
      "time_str": "13:28",
      "activity_type": "order_failed_timeout",
      "description": "runner_1 exceeded timeout before departure for Order 012; discarding",
      "order_id": "012",
      "location": "clubhouse",
      "runner_id": "runner_1"
    },
    {
      "timestamp_s": 23330,
      "time_str": "13:28",
      "activity_type": "order_assigned",
      "description": "Assigned Order 013 to runner_1",
      "order_id": "013",
      "location": "clubhouse",
      "runner_id": "runner_1"
    },
    {
      "timestamp_s": 23330,
      "time_str": "13:28",
      "activity_type": "order_failed_timeout",
      "description": "runner_1 received expired order 013; discarding",
      "order_id": "013",
      "location": "clubhouse",
      "runner_id": "runner_1"
    },
    {
      "timestamp_s": 23335,
      "time_str": "13:28",
      "activity_type": "order_assigned",
      "description": "Assigned Order 014 to runner_1",
      "order_id": "014",
      "location": "clubhouse",
      "runner_id": "runner_1"
    },
    {
      "timestamp_s": 23335,
      "time_str": "13:28",
      "activity_type": "prep_start",
      "description": "runner_1 started prep for Order 014 (Hole 7)",
      "order_id": "014",
      "location": "clubhouse",
      "runner_id": "runner_1"
    },
    {
      "timestamp_s": 23935,
      "time_str": "13:38",
      "activity_type": "prep_complete",
      "description": "runner_1 completed prep for Order 014",
      "order_id": "014",
      "location": "clubhouse",
      "runner_id": "runner_1"
    },
    {
      "timestamp_s": 23935,
      "time_str": "13:38",
      "activity_type": "delivery_start",
      "description": "runner_1 departing to Hole 11 (1593m, 4.7 min)",
      "order_id": "014",
      "location": "clubhouse",
      "runner_id": "runner_1"
    },
    {
      "timestamp_s": 24219.450205786176,
      "time_str": "13:43",
      "activity_type": "delivery_complete",
      "description": "runner_1 delivered Order 014 to Hole 11 (Total completion: 64.0 min)",
      "order_id": "014",
      "location": "hole_11",
      "runner_id": "runner_1"
    },
    {
      "timestamp_s": 24219.450205786176,
      "time_str": "13:43",
      "activity_type": "returning",
      "description": "runner_1 returning to clubhouse from hole_11 (9.5 min)",
      "order_id": "014",
      "location": "hole_11",
      "runner_id": "runner_1"
    },
    {
      "timestamp_s": 24790.878777214748,
      "time_str": "13:53",
      "activity_type": "arrived_clubhouse",
      "description": "runner_1 arrived at clubhouse after delivering Order 014",
      "order_id": "014",
      "location": "clubhouse",
      "runner_id": "runner_1"
    },
    {
      "timestamp_s": 24795,
      "time_str": "13:53",
      "activity_type": "order_assigned",
      "description": "Assigned Order 015 to runner_1",
      "order_id": "015",
      "location": "clubhouse",
      "runner_id": "runner_1"
    },
    {
      "timestamp_s": 24795,
      "time_str": "13:53",
      "activity_type": "order_failed_timeout",
      "description": "runner_1 received expired order 015; discarding",
      "order_id": "015",
      "location": "clubhouse",
      "runner_id": "runner_1"
    },
    {
      "timestamp_s": 24800,
      "time_str": "13:53",
      "activity_type": "order_assigned",
      "description": "Assigned Order 016 to runner_1",
      "order_id": "016",
      "location": "clubhouse",
      "runner_id": "runner_1"
    },
    {
      "timestamp_s": 24800,
      "time_str": "13:53",
      "activity_type": "order_failed_timeout",
      "description": "runner_1 received expired order 016; discarding",
      "order_id": "016",
      "location": "clubhouse",
      "runner_id": "runner_1"
    },
    {
      "timestamp_s": 24805,
      "time_str": "13:53",
      "activity_type": "order_assigned",
      "description": "Assigned Order 017 to runner_1",
      "order_id": "017",
      "location": "clubhouse",
      "runner_id": "runner_1"
    },
    {
      "timestamp_s": 24805,
      "time_str": "13:53",
      "activity_type": "order_failed_timeout",
      "description": "runner_1 received expired order 017; discarding",
      "order_id": "017",
      "location": "clubhouse",
      "runner_id": "runner_1"
    },
    {
      "timestamp_s": 24810,
      "time_str": "13:53",
      "activity_type": "order_assigned",
      "description": "Assigned Order 018 to runner_1",
      "order_id": "018",
      "location": "clubhouse",
      "runner_id": "runner_1"
    },
    {
      "timestamp_s": 24810,
      "time_str": "13:53",
      "activity_type": "order_failed_timeout",
      "description": "runner_1 received expired order 018; discarding",
      "order_id": "018",
      "location": "clubhouse",
      "runner_id": "runner_1"
    },
    {
      "timestamp_s": 24815,
      "time_str": "13:53",
      "activity_type": "order_assigned",
      "description": "Assigned Order 019 to runner_1",
      "order_id": "019",
      "location": "clubhouse",
      "runner_id": "runner_1"
    },
    {
      "timestamp_s": 24815,
      "time_str": "13:53",
      "activity_type": "prep_start",
      "description": "runner_1 started prep for Order 019 (Hole 17)",
      "order_id": "019",
      "location": "clubhouse",
      "runner_id": "runner_1"
    },
    {
      "timestamp_s": 25415,
      "time_str": "14:03",
      "activity_type": "prep_complete",
      "description": "runner_1 completed prep for Order 019",
      "order_id": "019",
      "location": "clubhouse",
      "runner_id": "runner_1"
    },
    {
      "timestamp_s": 25415,
      "time_str": "14:03",
      "activity_type": "order_failed_timeout",
      "description": "runner_1 exceeded timeout before departure for Order 019; discarding",
      "order_id": "019",
      "location": "clubhouse",
      "runner_id": "runner_1"
    },
    {
      "timestamp_s": 25415,
      "time_str": "14:03",
      "activity_type": "order_assigned",
      "description": "Assigned Order 020 to runner_1",
      "order_id": "020",
      "location": "clubhouse",
      "runner_id": "runner_1"
    },
    {
      "timestamp_s": 25415,
      "time_str": "14:03",
      "activity_type": "order_failed_timeout",
      "description": "runner_1 received expired order 020; discarding",
      "order_id": "020",
      "location": "clubhouse",
      "runner_id": "runner_1"
    },
    {
      "timestamp_s": 25420,
      "time_str": "14:03",
      "activity_type": "order_assigned",
      "description": "Assigned Order 021 to runner_1",
      "order_id": "021",
      "location": "clubhouse",
      "runner_id": "runner_1"
    },
    {
      "timestamp_s": 25420,
      "time_str": "14:03",
      "activity_type": "prep_start",
      "description": "runner_1 started prep for Order 021 (Hole 6)",
      "order_id": "021",
      "location": "clubhouse",
      "runner_id": "runner_1"
    },
    {
      "timestamp_s": 26020,
      "time_str": "14:13",
      "activity_type": "prep_complete",
      "description": "runner_1 completed prep for Order 021",
      "order_id": "021",
      "location": "clubhouse",
      "runner_id": "runner_1"
    },
    {
      "timestamp_s": 26020,
      "time_str": "14:13",
      "activity_type": "order_failed_timeout",
      "description": "runner_1 exceeded timeout before departure for Order 021; discarding",
      "order_id": "021",
      "location": "clubhouse",
      "runner_id": "runner_1"
    },
    {
      "timestamp_s": 26020,
      "time_str": "14:13",
      "activity_type": "order_assigned",
      "description": "Assigned Order 022 to runner_1",
      "order_id": "022",
      "location": "clubhouse",
      "runner_id": "runner_1"
    },
    {
      "timestamp_s": 26020,
      "time_str": "14:13",
      "activity_type": "order_failed_timeout",
      "description": "runner_1 received expired order 022; discarding",
      "order_id": "022",
      "location": "clubhouse",
      "runner_id": "runner_1"
    },
    {
      "timestamp_s": 26025,
      "time_str": "14:13",
      "activity_type": "order_assigned",
      "description": "Assigned Order 023 to runner_1",
      "order_id": "023",
      "location": "clubhouse",
      "runner_id": "runner_1"
    },
    {
      "timestamp_s": 26025,
      "time_str": "14:13",
      "activity_type": "prep_start",
      "description": "runner_1 started prep for Order 023 (Hole 18)",
      "order_id": "023",
      "location": "clubhouse",
      "runner_id": "runner_1"
    },
    {
      "timestamp_s": 26625,
      "time_str": "14:23",
      "activity_type": "prep_complete",
      "description": "runner_1 completed prep for Order 023",
      "order_id": "023",
      "location": "clubhouse",
      "runner_id": "runner_1"
    },
    {
      "timestamp_s": 26625,
      "time_str": "14:23",
      "activity_type": "order_failed_timeout",
      "description": "runner_1 exceeded timeout before departure for Order 023; discarding",
      "order_id": "023",
      "location": "clubhouse",
      "runner_id": "runner_1"
    },
    {
      "timestamp_s": 26625,
      "time_str": "14:23",
      "activity_type": "order_assigned",
      "description": "Assigned Order 024 to runner_1",
      "order_id": "024",
      "location": "clubhouse",
      "runner_id": "runner_1"
    },
    {
      "timestamp_s": 26625,
      "time_str": "14:23",
      "activity_type": "order_failed_timeout",
      "description": "runner_1 received expired order 024; discarding",
      "order_id": "024",
      "location": "clubhouse",
      "runner_id": "runner_1"
    },
    {
      "timestamp_s": 26630,
      "time_str": "14:23",
      "activity_type": "order_assigned",
      "description": "Assigned Order 025 to runner_1",
      "order_id": "025",
      "location": "clubhouse",
      "runner_id": "runner_1"
    },
    {
      "timestamp_s": 26630,
      "time_str": "14:23",
      "activity_type": "order_failed_timeout",
      "description": "runner_1 received expired order 025; discarding",
      "order_id": "025",
      "location": "clubhouse",
      "runner_id": "runner_1"
    },
    {
      "timestamp_s": 26635,
      "time_str": "14:23",
      "activity_type": "order_assigned",
      "description": "Assigned Order 026 to runner_1",
      "order_id": "026",
      "location": "clubhouse",
      "runner_id": "runner_1"
    },
    {
      "timestamp_s": 26635,
      "time_str": "14:23",
      "activity_type": "order_failed_timeout",
      "description": "runner_1 received expired order 026; discarding",
      "order_id": "026",
      "location": "clubhouse",
      "runner_id": "runner_1"
    },
    {
      "timestamp_s": 26640,
      "time_str": "14:24",
      "activity_type": "order_assigned",
      "description": "Assigned Order 027 to runner_1",
      "order_id": "027",
      "location": "clubhouse",
      "runner_id": "runner_1"
    },
    {
      "timestamp_s": 26640,
      "time_str": "14:24",
      "activity_type": "prep_start",
      "description": "runner_1 started prep for Order 027 (Hole 1)",
      "order_id": "027",
      "location": "clubhouse",
      "runner_id": "runner_1"
    },
    {
      "timestamp_s": 27240,
      "time_str": "14:34",
      "activity_type": "prep_complete",
      "description": "runner_1 completed prep for Order 027",
      "order_id": "027",
      "location": "clubhouse",
      "runner_id": "runner_1"
    },
    {
      "timestamp_s": 27240,
      "time_str": "14:34",
      "activity_type": "delivery_start",
      "description": "runner_1 departing to Hole 6 (3372m, 10.0 min)",
      "order_id": "027",
      "location": "clubhouse",
      "runner_id": "runner_1"
    },
    {
      "timestamp_s": 27842.111771418506,
      "time_str": "14:44",
      "activity_type": "delivery_complete",
      "description": "runner_1 delivered Order 027 to Hole 6 (Total completion: 64.9 min)",
      "order_id": "027",
      "location": "hole_6",
      "runner_id": "runner_1"
    },
    {
      "timestamp_s": 27842.111771418506,
      "time_str": "14:44",
      "activity_type": "returning",
      "description": "runner_1 returning to clubhouse from hole_6 (8.3 min)",
      "order_id": "027",
      "location": "hole_6",
      "runner_id": "runner_1"
    },
    {
      "timestamp_s": 28342.111771418506,
      "time_str": "14:52",
      "activity_type": "arrived_clubhouse",
      "description": "runner_1 arrived at clubhouse after delivering Order 027",
      "order_id": "027",
      "location": "clubhouse",
      "runner_id": "runner_1"
    },
    {
      "timestamp_s": 28345,
      "time_str": "14:52",
      "activity_type": "order_assigned",
      "description": "Assigned Order 028 to runner_1",
      "order_id": "028",
      "location": "clubhouse",
      "runner_id": "runner_1"
    },
    {
      "timestamp_s": 28345,
      "time_str": "14:52",
      "activity_type": "order_failed_timeout",
      "description": "runner_1 received expired order 028; discarding",
      "order_id": "028",
      "location": "clubhouse",
      "runner_id": "runner_1"
    },
    {
      "timestamp_s": 28350,
      "time_str": "14:52",
      "activity_type": "order_assigned",
      "description": "Assigned Order 029 to runner_1",
      "order_id": "029",
      "location": "clubhouse",
      "runner_id": "runner_1"
    },
    {
      "timestamp_s": 28350,
      "time_str": "14:52",
      "activity_type": "prep_start",
      "description": "runner_1 started prep for Order 029 (Hole 8)",
      "order_id": "029",
      "location": "clubhouse",
      "runner_id": "runner_1"
    },
    {
      "timestamp_s": 28950,
      "time_str": "15:02",
      "activity_type": "prep_complete",
      "description": "runner_1 completed prep for Order 029",
      "order_id": "029",
      "location": "clubhouse",
      "runner_id": "runner_1"
    },
    {
      "timestamp_s": 28950,
      "time_str": "15:02",
      "activity_type": "order_failed_timeout",
      "description": "runner_1 exceeded timeout before departure for Order 029; discarding",
      "order_id": "029",
      "location": "clubhouse",
      "runner_id": "runner_1"
    },
    {
      "timestamp_s": 28950,
      "time_str": "15:02",
      "activity_type": "order_assigned",
      "description": "Assigned Order 030 to runner_1",
      "order_id": "030",
      "location": "clubhouse",
      "runner_id": "runner_1"
    },
    {
      "timestamp_s": 28950,
      "time_str": "15:02",
      "activity_type": "prep_start",
      "description": "runner_1 started prep for Order 030 (Hole 2)",
      "order_id": "030",
      "location": "clubhouse",
      "runner_id": "runner_1"
    },
    {
      "timestamp_s": 29550,
      "time_str": "15:12",
      "activity_type": "prep_complete",
      "description": "runner_1 completed prep for Order 030",
      "order_id": "030",
      "location": "clubhouse",
      "runner_id": "runner_1"
    },
    {
      "timestamp_s": 29550,
      "time_str": "15:12",
      "activity_type": "order_failed_timeout",
      "description": "runner_1 exceeded timeout before departure for Order 030; discarding",
      "order_id": "030",
      "location": "clubhouse",
      "runner_id": "runner_1"
    },
    {
      "timestamp_s": 29550,
      "time_str": "15:12",
      "activity_type": "order_assigned",
      "description": "Assigned Order 031 to runner_1",
      "order_id": "031",
      "location": "clubhouse",
      "runner_id": "runner_1"
    },
    {
      "timestamp_s": 29550,
      "time_str": "15:12",
      "activity_type": "prep_start",
      "description": "runner_1 started prep for Order 031 (Hole 9)",
      "order_id": "031",
      "location": "clubhouse",
      "runner_id": "runner_1"
    },
    {
      "timestamp_s": 30150,
      "time_str": "15:22",
      "activity_type": "prep_complete",
      "description": "runner_1 completed prep for Order 031",
      "order_id": "031",
      "location": "clubhouse",
      "runner_id": "runner_1"
    },
    {
      "timestamp_s": 30150,
      "time_str": "15:22",
      "activity_type": "delivery_start",
      "description": "runner_1 departing to Hole 13 (1768m, 5.3 min)",
      "order_id": "031",
      "location": "clubhouse",
      "runner_id": "runner_1"
    },
    {
      "timestamp_s": 30465.74623204964,
      "time_str": "15:27",
      "activity_type": "delivery_complete",
      "description": "runner_1 delivered Order 031 to Hole 13 (Total completion: 61.1 min)",
      "order_id": "031",
      "location": "hole_13",
      "runner_id": "runner_1"
    },
    {
      "timestamp_s": 30465.74623204964,
      "time_str": "15:27",
      "activity_type": "returning",
      "description": "runner_1 returning to clubhouse from hole_13 (7.1 min)",
      "order_id": "031",
      "location": "hole_13",
      "runner_id": "runner_1"
    },
    {
      "timestamp_s": 30894.31766062107,
      "time_str": "15:34",
      "activity_type": "arrived_clubhouse",
      "description": "runner_1 arrived at clubhouse after delivering Order 031",
      "order_id": "031",
      "location": "clubhouse",
      "runner_id": "runner_1"
    },
    {
      "timestamp_s": 30895,
      "time_str": "15:34",
      "activity_type": "order_assigned",
      "description": "Assigned Order 032 to runner_1",
      "order_id": "032",
      "location": "clubhouse",
      "runner_id": "runner_1"
    },
    {
      "timestamp_s": 30895,
      "time_str": "15:34",
      "activity_type": "order_failed_timeout",
      "description": "runner_1 received expired order 032; discarding",
      "order_id": "032",
      "location": "clubhouse",
      "runner_id": "runner_1"
    },
    {
      "timestamp_s": 30900,
      "time_str": "15:35",
      "activity_type": "order_assigned",
      "description": "Assigned Order 033 to runner_1",
      "order_id": "033",
      "location": "clubhouse",
      "runner_id": "runner_1"
    },
    {
      "timestamp_s": 30900,
      "time_str": "15:35",
      "activity_type": "prep_start",
      "description": "runner_1 started prep for Order 033 (Hole 2)",
      "order_id": "033",
      "location": "clubhouse",
      "runner_id": "runner_1"
    },
    {
      "timestamp_s": 31500,
      "time_str": "15:45",
      "activity_type": "prep_complete",
      "description": "runner_1 completed prep for Order 033",
      "order_id": "033",
      "location": "clubhouse",
      "runner_id": "runner_1"
    },
    {
      "timestamp_s": 31500,
      "time_str": "15:45",
      "activity_type": "delivery_start",
      "description": "runner_1 departing to Hole 6 (2520m, 7.5 min)",
      "order_id": "033",
      "location": "clubhouse",
      "runner_id": "runner_1"
    },
    {
      "timestamp_s": 31950.006204049656,
      "time_str": "15:52",
      "activity_type": "delivery_complete",
      "description": "runner_1 delivered Order 033 to Hole 6 (Total completion: 58.5 min)",
      "order_id": "033",
      "location": "hole_6",
      "runner_id": "runner_1"
    },
    {
      "timestamp_s": 31950.006204049656,
      "time_str": "15:52",
      "activity_type": "returning",
      "description": "runner_1 returning to clubhouse from hole_6 (8.3 min)",
      "order_id": "033",
      "location": "hole_6",
      "runner_id": "runner_1"
    },
    {
      "timestamp_s": 32450.006204049656,
      "time_str": "16:00",
      "activity_type": "arrived_clubhouse",
      "description": "runner_1 arrived at clubhouse after delivering Order 033",
      "order_id": "033",
      "location": "clubhouse",
      "runner_id": "runner_1"
    },
    {
      "timestamp_s": 32455,
      "time_str": "16:00",
      "activity_type": "order_assigned",
      "description": "Assigned Order 034 to runner_1",
      "order_id": "034",
      "location": "clubhouse",
      "runner_id": "runner_1"
    },
    {
      "timestamp_s": 32455,
      "time_str": "16:00",
      "activity_type": "order_failed_timeout",
      "description": "runner_1 received expired order 034; discarding",
      "order_id": "034",
      "location": "clubhouse",
      "runner_id": "runner_1"
    },
    {
      "timestamp_s": 32460,
      "time_str": "16:01",
      "activity_type": "order_assigned",
      "description": "Assigned Order 035 to runner_1",
      "order_id": "035",
      "location": "clubhouse",
      "runner_id": "runner_1"
    },
    {
      "timestamp_s": 32460,
      "time_str": "16:01",
      "activity_type": "prep_start",
      "description": "runner_1 started prep for Order 035 (Hole 4)",
      "order_id": "035",
      "location": "clubhouse",
      "runner_id": "runner_1"
    },
    {
      "timestamp_s": 33060,
      "time_str": "16:11",
      "activity_type": "prep_complete",
      "description": "runner_1 completed prep for Order 035",
      "order_id": "035",
      "location": "clubhouse",
      "runner_id": "runner_1"
    },
    {
      "timestamp_s": 33060,
      "time_str": "16:11",
      "activity_type": "delivery_start",
      "description": "runner_1 departing to Hole 7 (1641m, 4.9 min)",
      "order_id": "035",
      "location": "clubhouse",
      "runner_id": "runner_1"
    },
    {
      "timestamp_s": 33353.08089153135,
      "time_str": "16:15",
      "activity_type": "delivery_complete",
      "description": "runner_1 delivered Order 035 to Hole 7 (Total completion: 52.7 min)",
      "order_id": "035",
      "location": "hole_7",
      "runner_id": "runner_1"
    },
    {
      "timestamp_s": 33353.08089153135,
      "time_str": "16:15",
      "activity_type": "returning",
      "description": "runner_1 returning to clubhouse from hole_7 (9.5 min)",
      "order_id": "035",
      "location": "hole_7",
      "runner_id": "runner_1"
    },
    {
      "timestamp_s": 33924.50946295992,
      "time_str": "16:25",
      "activity_type": "arrived_clubhouse",
      "description": "runner_1 arrived at clubhouse after delivering Order 035",
      "order_id": "035",
      "location": "clubhouse",
      "runner_id": "runner_1"
    },
    {
      "timestamp_s": 33925,
      "time_str": "16:25",
      "activity_type": "order_assigned",
      "description": "Assigned Order 036 to runner_1",
      "order_id": "036",
      "location": "clubhouse",
      "runner_id": "runner_1"
    },
    {
      "timestamp_s": 33925,
      "time_str": "16:25",
      "activity_type": "prep_start",
      "description": "runner_1 started prep for Order 036 (Hole 1)",
      "order_id": "036",
      "location": "clubhouse",
      "runner_id": "runner_1"
    },
    {
      "timestamp_s": 34525,
      "time_str": "16:35",
      "activity_type": "prep_complete",
      "description": "runner_1 completed prep for Order 036",
      "order_id": "036",
      "location": "clubhouse",
      "runner_id": "runner_1"
    },
    {
      "timestamp_s": 34525,
      "time_str": "16:35",
      "activity_type": "order_failed_timeout",
      "description": "runner_1 exceeded timeout before departure for Order 036; discarding",
      "order_id": "036",
      "location": "clubhouse",
      "runner_id": "runner_1"
    },
    {
      "timestamp_s": 34525,
      "time_str": "16:35",
      "activity_type": "order_assigned",
      "description": "Assigned Order 037 to runner_1",
      "order_id": "037",
      "location": "clubhouse",
      "runner_id": "runner_1"
    },
    {
      "timestamp_s": 34525,
      "time_str": "16:35",
      "activity_type": "prep_start",
      "description": "runner_1 started prep for Order 037 (Hole 18)",
      "order_id": "037",
      "location": "clubhouse",
      "runner_id": "runner_1"
    },
    {
      "timestamp_s": 35125,
      "time_str": "16:45",
      "activity_type": "prep_complete",
      "description": "runner_1 completed prep for Order 037",
      "order_id": "037",
      "location": "clubhouse",
      "runner_id": "runner_1"
    },
    {
      "timestamp_s": 35125,
      "time_str": "16:45",
      "activity_type": "delivery_start",
      "description": "runner_1 departing to Hole -1 (122m, 0.4 min)",
      "order_id": "037",
      "location": "clubhouse",
      "runner_id": "runner_1"
    },
    {
      "timestamp_s": 35146.86381039369,
      "time_str": "16:45",
      "activity_type": "delivery_complete",
      "description": "runner_1 delivered Order 037 to Hole -1 (Total completion: 55.1 min)",
      "order_id": "037",
      "location": "hole_-1",
      "runner_id": "runner_1"
    },
    {
      "timestamp_s": 35146.86381039369,
      "time_str": "16:45",
      "activity_type": "returning",
      "description": "runner_1 returning to clubhouse from hole_-1 (6.0 min)",
      "order_id": "037",
      "location": "hole_-1",
      "runner_id": "runner_1"
    },
    {
      "timestamp_s": 35504.006667536545,
      "time_str": "16:51",
      "activity_type": "arrived_clubhouse",
      "description": "runner_1 arrived at clubhouse after delivering Order 037",
      "order_id": "037",
      "location": "clubhouse",
      "runner_id": "runner_1"
    },
    {
      "timestamp_s": 35505,
      "time_str": "16:51",
      "activity_type": "order_assigned",
      "description": "Assigned Order 038 to runner_1",
      "order_id": "038",
      "location": "clubhouse",
      "runner_id": "runner_1"
    },
    {
      "timestamp_s": 35505,
      "time_str": "16:51",
      "activity_type": "prep_start",
      "description": "runner_1 started prep for Order 038 (Hole 6)",
      "order_id": "038",
      "location": "clubhouse",
      "runner_id": "runner_1"
    },
    {
      "timestamp_s": 36105,
      "time_str": "17:01",
      "activity_type": "prep_complete",
      "description": "runner_1 completed prep for Order 038",
      "order_id": "038",
      "location": "clubhouse",
      "runner_id": "runner_1"
    },
    {
      "timestamp_s": 36105,
      "time_str": "17:01",
      "activity_type": "delivery_start",
      "description": "runner_1 departing to Hole -1 (191m, 0.6 min)",
      "order_id": "038",
      "location": "clubhouse",
      "runner_id": "runner_1"
    },
    {
      "timestamp_s": 36139.16194618075,
      "time_str": "17:02",
      "activity_type": "delivery_complete",
      "description": "runner_1 delivered Order 038 to Hole -1 (Total completion: 44.1 min)",
      "order_id": "038",
      "location": "hole_-1",
      "runner_id": "runner_1"
    },
    {
      "timestamp_s": 36139.16194618075,
      "time_str": "17:02",
      "activity_type": "returning",
      "description": "runner_1 returning to clubhouse from hole_-1 (6.0 min)",
      "order_id": "038",
      "location": "hole_-1",
      "runner_id": "runner_1"
    },
    {
      "timestamp_s": 36496.304803323605,
      "time_str": "17:08",
      "activity_type": "arrived_clubhouse",
      "description": "runner_1 arrived at clubhouse after delivering Order 038",
      "order_id": "038",
      "location": "clubhouse",
      "runner_id": "runner_1"
    },
    {
      "timestamp_s": 36500,
      "time_str": "17:08",
      "activity_type": "order_assigned",
      "description": "Assigned Order 039 to runner_1",
      "order_id": "039",
      "location": "clubhouse",
      "runner_id": "runner_1"
    },
    {
      "timestamp_s": 36500,
      "time_str": "17:08",
      "activity_type": "prep_start",
      "description": "runner_1 started prep for Order 039 (Hole 18)",
      "order_id": "039",
      "location": "clubhouse",
      "runner_id": "runner_1"
    },
    {
      "timestamp_s": 37100,
      "time_str": "17:18",
      "activity_type": "prep_complete",
      "description": "runner_1 completed prep for Order 039",
      "order_id": "039",
      "location": "clubhouse",
      "runner_id": "runner_1"
    },
    {
      "timestamp_s": 37100,
      "time_str": "17:18",
      "activity_type": "delivery_start",
      "description": "runner_1 departing to Hole -1 (122m, 0.4 min)",
      "order_id": "039",
      "location": "clubhouse",
      "runner_id": "runner_1"
    },
    {
      "timestamp_s": 37121.86381039369,
      "time_str": "17:18",
      "activity_type": "delivery_complete",
      "description": "runner_1 delivered Order 039 to Hole -1 (Total completion: 59.2 min)",
      "order_id": "039",
      "location": "hole_-1",
      "runner_id": "runner_1"
    },
    {
      "timestamp_s": 37121.86381039369,
      "time_str": "17:18",
      "activity_type": "returning",
      "description": "runner_1 returning to clubhouse from hole_-1 (6.0 min)",
      "order_id": "039",
      "location": "hole_-1",
      "runner_id": "runner_1"
    },
    {
      "timestamp_s": 37479.006667536545,
      "time_str": "17:24",
      "activity_type": "arrived_clubhouse",
      "description": "runner_1 arrived at clubhouse after delivering Order 039",
      "order_id": "039",
      "location": "clubhouse",
      "runner_id": "runner_1"
    },
    {
      "timestamp_s": 37480,
      "time_str": "17:24",
      "activity_type": "order_assigned",
      "description": "Assigned Order 040 to runner_1",
      "order_id": "040",
      "location": "clubhouse",
      "runner_id": "runner_1"
    },
    {
      "timestamp_s": 37480,
      "time_str": "17:24",
      "activity_type": "prep_start",
      "description": "runner_1 started prep for Order 040 (Hole 14)",
      "order_id": "040",
      "location": "clubhouse",
      "runner_id": "runner_1"
    },
    {
      "timestamp_s": 38080,
      "time_str": "17:34",
      "activity_type": "prep_complete",
      "description": "runner_1 completed prep for Order 040",
      "order_id": "040",
      "location": "clubhouse",
      "runner_id": "runner_1"
    },
    {
      "timestamp_s": 38080,
      "time_str": "17:34",
      "activity_type": "delivery_start",
      "description": "runner_1 departing to Hole -1 (229m, 0.7 min)",
      "order_id": "040",
      "location": "clubhouse",
      "runner_id": "runner_1"
    },
    {
      "timestamp_s": 38120.83013455671,
      "time_str": "17:35",
      "activity_type": "delivery_complete",
      "description": "runner_1 delivered Order 040 to Hole -1 (Total completion: 59.5 min)",
      "order_id": "040",
      "location": "hole_-1",
      "runner_id": "runner_1"
    },
    {
      "timestamp_s": 38120.83013455671,
      "time_str": "17:35",
      "activity_type": "returning",
      "description": "runner_1 returning to clubhouse from hole_-1 (6.0 min)",
      "order_id": "040",
      "location": "hole_-1",
      "runner_id": "runner_1"
    },
    {
      "timestamp_s": 38477.972991699564,
      "time_str": "17:41",
      "activity_type": "arrived_clubhouse",
      "description": "runner_1 arrived at clubhouse after delivering Order 040",
      "order_id": "040",
      "location": "clubhouse",
      "runner_id": "runner_1"
    },
    {
      "timestamp_s": 38480,
      "time_str": "17:41",
      "activity_type": "order_assigned",
      "description": "Assigned Order 041 to runner_1",
      "order_id": "041",
      "location": "clubhouse",
      "runner_id": "runner_1"
    },
    {
      "timestamp_s": 38480,
      "time_str": "17:41",
      "activity_type": "prep_start",
      "description": "runner_1 started prep for Order 041 (Hole 5)",
      "order_id": "041",
      "location": "clubhouse",
      "runner_id": "runner_1"
    },
    {
      "timestamp_s": 39080,
      "time_str": "17:51",
      "activity_type": "prep_complete",
      "description": "runner_1 completed prep for Order 041",
      "order_id": "041",
      "location": "clubhouse",
      "runner_id": "runner_1"
    },
    {
      "timestamp_s": 39080,
      "time_str": "17:51",
      "activity_type": "delivery_start",
      "description": "runner_1 departing to Hole 9 (958m, 2.9 min)",
      "order_id": "041",
      "location": "clubhouse",
      "runner_id": "runner_1"
    },
    {
      "timestamp_s": 39251.03162399511,
      "time_str": "17:54",
      "activity_type": "delivery_complete",
      "description": "runner_1 delivered Order 041 to Hole 9 (Total completion: 60.4 min)",
      "order_id": "041",
      "location": "hole_9",
      "runner_id": "runner_1"
    },
    {
      "timestamp_s": 39251.03162399511,
      "time_str": "17:54",
      "activity_type": "returning",
      "description": "runner_1 returning to clubhouse from hole_9 (11.9 min)",
      "order_id": "041",
      "location": "hole_9",
      "runner_id": "runner_1"
    },
    {
      "timestamp_s": 39965.31733828083,
      "time_str": "18:06",
      "activity_type": "arrived_clubhouse",
      "description": "runner_1 arrived at clubhouse after delivering Order 041",
      "order_id": "041",
      "location": "clubhouse",
      "runner_id": "runner_1"
    },
    {
      "timestamp_s": 39965.31733828083,
      "time_str": "18:06",
      "activity_type": "service_closed",
      "description": "runner_1 shift ended",
      "order_id": null,
      "location": "clubhouse",
      "runner_id": "runner_1"
    },
    {
      "timestamp_s": 39970,
      "time_str": "18:06",
      "activity_type": "order_assigned",
      "description": "Assigned Order 042 to runner_1",
      "order_id": "042",
      "location": "clubhouse",
      "runner_id": "runner_1"
    }
  ],
  "metadata": {
    "prep_time_min": 10,
    "runner_speed_mps": 2.8,
    "num_groups": 68,
    "num_runners": 1,
    "course_dir": "C:\\Main\\GIT\\simulation\\courses\\pinetree_country_club",
    "service_open_s": 14400,
    "service_close_s": 39600,
    "blocked_holes": [],
    "variant_key": "none"
  }
}