{
  "success": true,
  "simulation_type": "multi_golfer_single_runner",
  "orders": [
    {
      "order_id": "001",
      "golfer_group_id": 8,
      "golfer_id": "G8",
      "hole_num": 11,
      "order_time_s": 14433,
      "status": "processed",
      "total_completion_time_s": 1063.1770921118477
    },
    {
      "order_id": "002",
      "golfer_group_id": 15,
      "golfer_id": "G15",
      "hole_num": 6,
      "order_time_s": 14533,
      "status": "processed",
      "total_completion_time_s": 2085.6374239937395
    },
    {
      "order_id": "003",
      "golfer_group_id": 15,
      "golfer_id": "G15",
      "hole_num": 7,
      "order_time_s": 14788,
      "status": "processed",
      "total_completion_time_s": 3385.289669274345
    },
    {
      "order_id": "004",
      "golfer_group_id": 13,
      "golfer_id": "G13",
      "hole_num": 9,
      "order_time_s": 15524,
      "status": "failed",
      "total_completion_time_s": 0.0
    },
    {
      "order_id": "005",
      "golfer_group_id": 2,
      "golfer_id": "G2",
      "hole_num": 17,
      "order_time_s": 15924,
      "status": "failed",
      "total_completion_time_s": 0.0
    },
    {
      "order_id": "006",
      "golfer_group_id": 14,
      "golfer_id": "G14",
      "hole_num": 9,
      "order_time_s": 16015,
      "status": "failed",
      "total_completion_time_s": 0.0
    },
    {
      "order_id": "007",
      "golfer_group_id": 5,
      "golfer_id": "G5",
      "hole_num": 17,
      "order_time_s": 16558,
      "status": "failed",
      "total_completion_time_s": 0.0
    },
    {
      "order_id": "008",
      "golfer_group_id": 8,
      "golfer_id": "G8",
      "hole_num": 15,
      "order_time_s": 16949,
      "status": "failed",
      "total_completion_time_s": 0.0
    },
    {
      "order_id": "009",
      "golfer_group_id": 11,
      "golfer_id": "G11",
      "hole_num": 14,
      "order_time_s": 17801,
      "status": "failed",
      "total_completion_time_s": 0.0
    },
    {
      "order_id": "010",
      "golfer_group_id": 10,
      "golfer_id": "G10",
      "hole_num": 16,
      "order_time_s": 18530,
      "status": "failed",
      "total_completion_time_s": 0.0
    },
    {
      "order_id": "011",
      "golfer_group_id": 9,
      "golfer_id": "G9",
      "hole_num": 17,
      "order_time_s": 18683,
      "status": "failed",
      "total_completion_time_s": 0.0
    },
    {
      "order_id": "012",
      "golfer_group_id": 10,
      "golfer_id": "G10",
      "hole_num": 17,
      "order_time_s": 18988,
      "status": "failed",
      "total_completion_time_s": 0.0
    },
    {
      "order_id": "013",
      "golfer_group_id": 10,
      "golfer_id": "G10",
      "hole_num": 17,
      "order_time_s": 19279,
      "status": "failed",
      "total_completion_time_s": 0.0
    },
    {
      "order_id": "014",
      "golfer_group_id": 20,
      "golfer_id": "G20",
      "hole_num": 9,
      "order_time_s": 19684,
      "status": "failed",
      "total_completion_time_s": 0.0
    },
    {
      "order_id": "015",
      "golfer_group_id": 10,
      "golfer_id": "G10",
      "hole_num": 17,
      "order_time_s": 20002,
      "status": "failed",
      "total_completion_time_s": 0.0
    },
    {
      "order_id": "016",
      "golfer_group_id": 20,
      "golfer_id": "G20",
      "hole_num": 10,
      "order_time_s": 20383,
      "status": "failed",
      "total_completion_time_s": 0.0
    },
    {
      "order_id": "017",
      "golfer_group_id": 10,
      "golfer_id": "G10",
      "hole_num": 18,
      "order_time_s": 20494,
      "status": "failed",
      "total_completion_time_s": 0.0
    },
    {
      "order_id": "018",
      "golfer_group_id": 16,
      "golfer_id": "G16",
      "hole_num": 15,
      "order_time_s": 20904,
      "status": "failed",
      "total_completion_time_s": 0.0
    },
    {
      "order_id": "019",
      "golfer_group_id": 16,
      "golfer_id": "G16",
      "hole_num": 15,
      "order_time_s": 20966,
      "status": "failed",
      "total_completion_time_s": 0.0
    },
    {
      "order_id": "020",
      "golfer_group_id": 21,
      "golfer_id": "G21",
      "hole_num": 10,
      "order_time_s": 21066,
      "status": "failed",
      "total_completion_time_s": 0.0
    },
    {
      "order_id": "021",
      "golfer_group_id": 20,
      "golfer_id": "G20",
      "hole_num": 12,
      "order_time_s": 22069,
      "status": "processed",
      "total_completion_time_s": 3413.142057546138
    },
    {
      "order_id": "022",
      "golfer_group_id": 19,
      "golfer_id": "G19",
      "hole_num": 14,
      "order_time_s": 22602,
      "status": "processed",
      "total_completion_time_s": 3573.1801507022756
    },
    {
      "order_id": "023",
      "golfer_group_id": 28,
      "golfer_id": "G28",
      "hole_num": 8,
      "order_time_s": 23120,
      "status": "failed",
      "total_completion_time_s": 0.0
    },
    {
      "order_id": "024",
      "golfer_group_id": 30,
      "golfer_id": "G30",
      "hole_num": 8,
      "order_time_s": 23919,
      "status": "processed",
      "total_completion_time_s": 3971.576207777147
    },
    {
      "order_id": "025",
      "golfer_group_id": 25,
      "golfer_id": "G25",
      "hole_num": 12,
      "order_time_s": 24012,
      "status": "failed",
      "total_completion_time_s": 0.0
    },
    {
      "order_id": "026",
      "golfer_group_id": 19,
      "golfer_id": "G19",
      "hole_num": 17,
      "order_time_s": 24554,
      "status": "failed",
      "total_completion_time_s": 0.0
    },
    {
      "order_id": "027",
      "golfer_group_id": 23,
      "golfer_id": "G23",
      "hole_num": 14,
      "order_time_s": 24565,
      "status": "failed",
      "total_completion_time_s": 0.0
    },
    {
      "order_id": "028",
      "golfer_group_id": 25,
      "golfer_id": "G25",
      "hole_num": 12,
      "order_time_s": 24614,
      "status": "failed",
      "total_completion_time_s": 0.0
    },
    {
      "order_id": "029",
      "golfer_group_id": 18,
      "golfer_id": "G18",
      "hole_num": 18,
      "order_time_s": 24838,
      "status": "failed",
      "total_completion_time_s": 0.0
    },
    {
      "order_id": "030",
      "golfer_group_id": 21,
      "golfer_id": "G21",
      "hole_num": 17,
      "order_time_s": 25990,
      "status": "processed",
      "total_completion_time_s": 3500.1801507022756
    },
    {
      "order_id": "031",
      "golfer_group_id": 30,
      "golfer_id": "G30",
      "hole_num": 11,
      "order_time_s": 26216,
      "status": "failed",
      "total_completion_time_s": 0.0
    },
    {
      "order_id": "032",
      "golfer_group_id": 33,
      "golfer_id": "G33",
      "hole_num": 9,
      "order_time_s": 26435,
      "status": "failed",
      "total_completion_time_s": 0.0
    },
    {
      "order_id": "033",
      "golfer_group_id": 36,
      "golfer_id": "G36",
      "hole_num": 8,
      "order_time_s": 27400,
      "status": "processed",
      "total_completion_time_s": 3810.576207777147
    },
    {
      "order_id": "034",
      "golfer_group_id": 32,
      "golfer_id": "G32",
      "hole_num": 12,
      "order_time_s": 28481,
      "status": "failed",
      "total_completion_time_s": 0.0
    },
    {
      "order_id": "035",
      "golfer_group_id": 39,
      "golfer_id": "G39",
      "hole_num": 8,
      "order_time_s": 28931,
      "status": "failed",
      "total_completion_time_s": 0.0
    },
    {
      "order_id": "036",
      "golfer_group_id": 28,
      "golfer_id": "G28",
      "hole_num": 18,
      "order_time_s": 30495,
      "status": "processed",
      "total_completion_time_s": 2895.1801507022756
    },
    {
      "order_id": "037",
      "golfer_group_id": 29,
      "golfer_id": "G29",
      "hole_num": 18,
      "order_time_s": 31076,
      "status": "processed",
      "total_completion_time_s": 3009.1801507022756
    },
    {
      "order_id": "038",
      "golfer_group_id": 39,
      "golfer_id": "G39",
      "hole_num": 14,
      "order_time_s": 33040,
      "status": "processed",
      "total_completion_time_s": 2013.7253619356925
    },
    {
      "order_id": "039",
      "golfer_group_id": 48,
      "golfer_id": "G48",
      "hole_num": 7,
      "order_time_s": 33235,
      "status": "processed",
      "total_completion_time_s": 2785.0726414346136
    },
    {
      "order_id": "040",
      "golfer_group_id": 36,
      "golfer_id": "G36",
      "hole_num": 17,
      "order_time_s": 33436,
      "status": "failed",
      "total_completion_time_s": 0.0
    },
    {
      "order_id": "041",
      "golfer_group_id": 40,
      "golfer_id": "G40",
      "hole_num": 14,
      "order_time_s": 34091,
      "status": "failed",
      "total_completion_time_s": 0.0
    },
    {
      "order_id": "042",
      "golfer_group_id": 50,
      "golfer_id": "G50",
      "hole_num": 9,
      "order_time_s": 35650,
      "status": "processed",
      "total_completion_time_s": 3115.5762077771506
    },
    {
      "order_id": "043",
      "golfer_group_id": 53,
      "golfer_id": "G53",
      "hole_num": 7,
      "order_time_s": 36059,
      "status": "failed",
      "total_completion_time_s": 0.0
    },
    {
      "order_id": "044",
      "golfer_group_id": 40,
      "golfer_id": "G40",
      "hole_num": 18,
      "order_time_s": 36711,
      "status": "pending",
      "total_completion_time_s": 0.0
    },
    {
      "order_id": "045",
      "golfer_group_id": 40,
      "golfer_id": "G40",
      "hole_num": 18,
      "order_time_s": 36731,
      "status": "pending",
      "total_completion_time_s": 0.0
    },
    {
      "order_id": "046",
      "golfer_group_id": 43,
      "golfer_id": "G43",
      "hole_num": 16,
      "order_time_s": 36913,
      "status": "pending",
      "total_completion_time_s": 0.0
    },
    {
      "order_id": "047",
      "golfer_group_id": 40,
      "golfer_id": "G40",
      "hole_num": 18,
      "order_time_s": 36967,
      "status": "pending",
      "total_completion_time_s": 0.0
    },
    {
      "order_id": "048",
      "golfer_group_id": 44,
      "golfer_id": "G44",
      "hole_num": 16,
      "order_time_s": 37168,
      "status": "pending",
      "total_completion_time_s": 0.0
    },
    {
      "order_id": "049",
      "golfer_group_id": 52,
      "golfer_id": "G52",
      "hole_num": 10,
      "order_time_s": 37376,
      "status": "pending",
      "total_completion_time_s": 0.0
    },
    {
      "order_id": "050",
      "golfer_group_id": 51,
      "golfer_id": "G51",
      "hole_num": 12,
      "order_time_s": 38079,
      "status": "pending",
      "total_completion_time_s": 0.0
    }
  ],
  "orders_all": [
    {
      "order_id": "001",
      "golfer_group_id": 8,
      "golfer_id": "G8",
      "hole_num": 11,
      "order_time_s": 14433,
      "status": "processed",
      "total_completion_time_s": 1063.1770921118477
    },
    {
      "order_id": "002",
      "golfer_group_id": 15,
      "golfer_id": "G15",
      "hole_num": 6,
      "order_time_s": 14533,
      "status": "processed",
      "total_completion_time_s": 2085.6374239937395
    },
    {
      "order_id": "003",
      "golfer_group_id": 15,
      "golfer_id": "G15",
      "hole_num": 7,
      "order_time_s": 14788,
      "status": "processed",
      "total_completion_time_s": 3385.289669274345
    },
    {
      "order_id": "004",
      "golfer_group_id": 13,
      "golfer_id": "G13",
      "hole_num": 9,
      "order_time_s": 15524,
      "status": "failed",
      "total_completion_time_s": 0.0
    },
    {
      "order_id": "005",
      "golfer_group_id": 2,
      "golfer_id": "G2",
      "hole_num": 17,
      "order_time_s": 15924,
      "status": "failed",
      "total_completion_time_s": 0.0
    },
    {
      "order_id": "006",
      "golfer_group_id": 14,
      "golfer_id": "G14",
      "hole_num": 9,
      "order_time_s": 16015,
      "status": "failed",
      "total_completion_time_s": 0.0
    },
    {
      "order_id": "007",
      "golfer_group_id": 5,
      "golfer_id": "G5",
      "hole_num": 17,
      "order_time_s": 16558,
      "status": "failed",
      "total_completion_time_s": 0.0
    },
    {
      "order_id": "008",
      "golfer_group_id": 8,
      "golfer_id": "G8",
      "hole_num": 15,
      "order_time_s": 16949,
      "status": "failed",
      "total_completion_time_s": 0.0
    },
    {
      "order_id": "009",
      "golfer_group_id": 11,
      "golfer_id": "G11",
      "hole_num": 14,
      "order_time_s": 17801,
      "status": "failed",
      "total_completion_time_s": 0.0
    },
    {
      "order_id": "010",
      "golfer_group_id": 10,
      "golfer_id": "G10",
      "hole_num": 16,
      "order_time_s": 18530,
      "status": "failed",
      "total_completion_time_s": 0.0
    },
    {
      "order_id": "011",
      "golfer_group_id": 9,
      "golfer_id": "G9",
      "hole_num": 17,
      "order_time_s": 18683,
      "status": "failed",
      "total_completion_time_s": 0.0
    },
    {
      "order_id": "012",
      "golfer_group_id": 10,
      "golfer_id": "G10",
      "hole_num": 17,
      "order_time_s": 18988,
      "status": "failed",
      "total_completion_time_s": 0.0
    },
    {
      "order_id": "013",
      "golfer_group_id": 10,
      "golfer_id": "G10",
      "hole_num": 17,
      "order_time_s": 19279,
      "status": "failed",
      "total_completion_time_s": 0.0
    },
    {
      "order_id": "014",
      "golfer_group_id": 20,
      "golfer_id": "G20",
      "hole_num": 9,
      "order_time_s": 19684,
      "status": "failed",
      "total_completion_time_s": 0.0
    },
    {
      "order_id": "015",
      "golfer_group_id": 10,
      "golfer_id": "G10",
      "hole_num": 17,
      "order_time_s": 20002,
      "status": "failed",
      "total_completion_time_s": 0.0
    },
    {
      "order_id": "016",
      "golfer_group_id": 20,
      "golfer_id": "G20",
      "hole_num": 10,
      "order_time_s": 20383,
      "status": "failed",
      "total_completion_time_s": 0.0
    },
    {
      "order_id": "017",
      "golfer_group_id": 10,
      "golfer_id": "G10",
      "hole_num": 18,
      "order_time_s": 20494,
      "status": "failed",
      "total_completion_time_s": 0.0
    },
    {
      "order_id": "018",
      "golfer_group_id": 16,
      "golfer_id": "G16",
      "hole_num": 15,
      "order_time_s": 20904,
      "status": "failed",
      "total_completion_time_s": 0.0
    },
    {
      "order_id": "019",
      "golfer_group_id": 16,
      "golfer_id": "G16",
      "hole_num": 15,
      "order_time_s": 20966,
      "status": "failed",
      "total_completion_time_s": 0.0
    },
    {
      "order_id": "020",
      "golfer_group_id": 21,
      "golfer_id": "G21",
      "hole_num": 10,
      "order_time_s": 21066,
      "status": "failed",
      "total_completion_time_s": 0.0
    },
    {
      "order_id": "021",
      "golfer_group_id": 20,
      "golfer_id": "G20",
      "hole_num": 12,
      "order_time_s": 22069,
      "status": "processed",
      "total_completion_time_s": 3413.142057546138
    },
    {
      "order_id": "022",
      "golfer_group_id": 19,
      "golfer_id": "G19",
      "hole_num": 14,
      "order_time_s": 22602,
      "status": "processed",
      "total_completion_time_s": 3573.1801507022756
    },
    {
      "order_id": "023",
      "golfer_group_id": 28,
      "golfer_id": "G28",
      "hole_num": 8,
      "order_time_s": 23120,
      "status": "failed",
      "total_completion_time_s": 0.0
    },
    {
      "order_id": "024",
      "golfer_group_id": 30,
      "golfer_id": "G30",
      "hole_num": 8,
      "order_time_s": 23919,
      "status": "processed",
      "total_completion_time_s": 3971.576207777147
    },
    {
      "order_id": "025",
      "golfer_group_id": 25,
      "golfer_id": "G25",
      "hole_num": 12,
      "order_time_s": 24012,
      "status": "failed",
      "total_completion_time_s": 0.0
    },
    {
      "order_id": "026",
      "golfer_group_id": 19,
      "golfer_id": "G19",
      "hole_num": 17,
      "order_time_s": 24554,
      "status": "failed",
      "total_completion_time_s": 0.0
    },
    {
      "order_id": "027",
      "golfer_group_id": 23,
      "golfer_id": "G23",
      "hole_num": 14,
      "order_time_s": 24565,
      "status": "failed",
      "total_completion_time_s": 0.0
    },
    {
      "order_id": "028",
      "golfer_group_id": 25,
      "golfer_id": "G25",
      "hole_num": 12,
      "order_time_s": 24614,
      "status": "failed",
      "total_completion_time_s": 0.0
    },
    {
      "order_id": "029",
      "golfer_group_id": 18,
      "golfer_id": "G18",
      "hole_num": 18,
      "order_time_s": 24838,
      "status": "failed",
      "total_completion_time_s": 0.0
    },
    {
      "order_id": "030",
      "golfer_group_id": 21,
      "golfer_id": "G21",
      "hole_num": 17,
      "order_time_s": 25990,
      "status": "processed",
      "total_completion_time_s": 3500.1801507022756
    },
    {
      "order_id": "031",
      "golfer_group_id": 30,
      "golfer_id": "G30",
      "hole_num": 11,
      "order_time_s": 26216,
      "status": "failed",
      "total_completion_time_s": 0.0
    },
    {
      "order_id": "032",
      "golfer_group_id": 33,
      "golfer_id": "G33",
      "hole_num": 9,
      "order_time_s": 26435,
      "status": "failed",
      "total_completion_time_s": 0.0
    },
    {
      "order_id": "033",
      "golfer_group_id": 36,
      "golfer_id": "G36",
      "hole_num": 8,
      "order_time_s": 27400,
      "status": "processed",
      "total_completion_time_s": 3810.576207777147
    },
    {
      "order_id": "034",
      "golfer_group_id": 32,
      "golfer_id": "G32",
      "hole_num": 12,
      "order_time_s": 28481,
      "status": "failed",
      "total_completion_time_s": 0.0
    },
    {
      "order_id": "035",
      "golfer_group_id": 39,
      "golfer_id": "G39",
      "hole_num": 8,
      "order_time_s": 28931,
      "status": "failed",
      "total_completion_time_s": 0.0
    },
    {
      "order_id": "036",
      "golfer_group_id": 28,
      "golfer_id": "G28",
      "hole_num": 18,
      "order_time_s": 30495,
      "status": "processed",
      "total_completion_time_s": 2895.1801507022756
    },
    {
      "order_id": "037",
      "golfer_group_id": 29,
      "golfer_id": "G29",
      "hole_num": 18,
      "order_time_s": 31076,
      "status": "processed",
      "total_completion_time_s": 3009.1801507022756
    },
    {
      "order_id": "038",
      "golfer_group_id": 39,
      "golfer_id": "G39",
      "hole_num": 14,
      "order_time_s": 33040,
      "status": "processed",
      "total_completion_time_s": 2013.7253619356925
    },
    {
      "order_id": "039",
      "golfer_group_id": 48,
      "golfer_id": "G48",
      "hole_num": 7,
      "order_time_s": 33235,
      "status": "processed",
      "total_completion_time_s": 2785.0726414346136
    },
    {
      "order_id": "040",
      "golfer_group_id": 36,
      "golfer_id": "G36",
      "hole_num": 17,
      "order_time_s": 33436,
      "status": "failed",
      "total_completion_time_s": 0.0
    },
    {
      "order_id": "041",
      "golfer_group_id": 40,
      "golfer_id": "G40",
      "hole_num": 14,
      "order_time_s": 34091,
      "status": "failed",
      "total_completion_time_s": 0.0
    },
    {
      "order_id": "042",
      "golfer_group_id": 50,
      "golfer_id": "G50",
      "hole_num": 9,
      "order_time_s": 35650,
      "status": "processed",
      "total_completion_time_s": 3115.5762077771506
    },
    {
      "order_id": "043",
      "golfer_group_id": 53,
      "golfer_id": "G53",
      "hole_num": 7,
      "order_time_s": 36059,
      "status": "failed",
      "total_completion_time_s": 0.0
    },
    {
      "order_id": "044",
      "golfer_group_id": 40,
      "golfer_id": "G40",
      "hole_num": 18,
      "order_time_s": 36711,
      "status": "pending",
      "total_completion_time_s": 0.0
    },
    {
      "order_id": "045",
      "golfer_group_id": 40,
      "golfer_id": "G40",
      "hole_num": 18,
      "order_time_s": 36731,
      "status": "pending",
      "total_completion_time_s": 0.0
    },
    {
      "order_id": "046",
      "golfer_group_id": 43,
      "golfer_id": "G43",
      "hole_num": 16,
      "order_time_s": 36913,
      "status": "pending",
      "total_completion_time_s": 0.0
    },
    {
      "order_id": "047",
      "golfer_group_id": 40,
      "golfer_id": "G40",
      "hole_num": 18,
      "order_time_s": 36967,
      "status": "pending",
      "total_completion_time_s": 0.0
    },
    {
      "order_id": "048",
      "golfer_group_id": 44,
      "golfer_id": "G44",
      "hole_num": 16,
      "order_time_s": 37168,
      "status": "pending",
      "total_completion_time_s": 0.0
    },
    {
      "order_id": "049",
      "golfer_group_id": 52,
      "golfer_id": "G52",
      "hole_num": 10,
      "order_time_s": 37376,
      "status": "pending",
      "total_completion_time_s": 0.0
    },
    {
      "order_id": "050",
      "golfer_group_id": 51,
      "golfer_id": "G51",
      "hole_num": 12,
      "order_time_s": 38079,
      "status": "pending",
      "total_completion_time_s": 0.0
    }
  ],
  "delivery_stats": [
    {
      "order_id": "001",
      "golfer_group_id": 8,
      "hole_num": 13,
      "placed_hole_num": 11,
      "order_time_s": 14433,
      "queue_delay_s": 2,
      "prep_time_s": 600,
      "delivery_time_s": 461.17709211184774,
      "return_time_s": 428.5714285714286,
      "total_drive_time_s": 889.7485206832764,
      "delivery_distance_m": 2582.5917158263455,
      "total_completion_time_s": 1063.1770921118477,
      "delivered_at_time_s": 15496.177092111848,
      "runner_id": "runner_1",
      "order_node_idx": 120,
      "predicted_delivery_node_idx": 157,
      "actual_delivery_node_idx": 157,
      "trip_to_golfer": {
        "nodes": [
          "7",
          8,
          9,
          10,
          11,
          120,
          121,
          122,
          123,
          124,
          125,
          126,
          127,
          128,
          129,
          130,
          131,
          132,
          133,
          134,
          142,
          143,
          144,
          145,
          146,
          147,
          148,
          149,
          150,
          151,
          152,
          153,
          154,
          155,
          156,
          157,
          158,
          159,
          160,
          161,
          162,
          163,
          "164"
        ],
        "length_m": 1291.2958579131732,
        "time_s": 461.1770921118476,
        "efficiency": null,
        "routing_type": "optimal"
      },
      "trip_back": {
        "nodes": [
          "164",
          163,
          162,
          161,
          160,
          159,
          158,
          157,
          156,
          155,
          154,
          153,
          152,
          151,
          150,
          149,
          148,
          147,
          146,
          145,
          144,
          143,
          142,
          134,
          133,
          132,
          131,
          130,
          129,
          128,
          127,
          126,
          125,
          124,
          123,
          122,
          121,
          120,
          11,
          10,
          9,
          8,
          "7"
        ],
        "length_m": 1291.2958579131725,
        "time_s": 461.17709211184734,
        "efficiency": null,
        "routing_type": "optimal"
      },
      "predicted_delivery_location": [
        -78.35835276672037,
        38.01331673063973
      ]
    },
    {
      "order_id": "002",
      "golfer_group_id": 15,
      "hole_num": 10,
      "placed_hole_num": 6,
      "order_time_s": 14533,
      "queue_delay_s": 1392,
      "prep_time_s": 600,
      "delivery_time_s": 93.6374239937395,
      "return_time_s": 642.8571428571429,
      "total_drive_time_s": 736.4945668508824,
      "delivery_distance_m": 524.3695743649448,
      "total_completion_time_s": 2085.6374239937395,
      "delivered_at_time_s": 16618.63742399374,
      "runner_id": "runner_1",
      "order_node_idx": 60,
      "predicted_delivery_node_idx": 117,
      "actual_delivery_node_idx": 117,
      "trip_to_golfer": {
        "nodes": [
          "7",
          8,
          9,
          10,
          11,
          120,
          121,
          122,
          123,
          "124"
        ],
        "length_m": 262.18478718247246,
        "time_s": 93.63742399374017,
        "efficiency": null,
        "routing_type": "optimal"
      },
      "trip_back": {
        "nodes": [
          "124",
          123,
          122,
          121,
          120,
          11,
          10,
          9,
          8,
          "7"
        ],
        "length_m": 262.1847871824724,
        "time_s": 93.63742399374016,
        "efficiency": null,
        "routing_type": "optimal"
      },
      "predicted_delivery_location": [
        -78.36422047549085,
        38.01686683744524
      ]
    },
    {
      "order_id": "003",
      "golfer_group_id": 15,
      "hole_num": 12,
      "placed_hole_num": 7,
      "order_time_s": 14788,
      "queue_delay_s": 2477,
      "prep_time_s": 600,
      "delivery_time_s": 308.2896692743452,
      "return_time_s": 500.00000000000006,
      "total_drive_time_s": 808.2896692743452,
      "delivery_distance_m": 1726.4221479363332,
      "total_completion_time_s": 3385.289669274345,
      "delivered_at_time_s": 18173.289669274345,
      "runner_id": "runner_1",
      "order_node_idx": 72,
      "predicted_delivery_node_idx": 143,
      "actual_delivery_node_idx": 143,
      "trip_to_golfer": {
        "nodes": [
          "7",
          8,
          9,
          10,
          11,
          120,
          121,
          122,
          123,
          124,
          125,
          126,
          127,
          128,
          129,
          130,
          131,
          132,
          133,
          134,
          142,
          143,
          144,
          145,
          146,
          147,
          148,
          149,
          "150"
        ],
        "length_m": 863.2110739681667,
        "time_s": 308.2896692743453,
        "efficiency": null,
        "routing_type": "optimal"
      },
      "trip_back": {
        "nodes": [
          "150",
          149,
          148,
          147,
          146,
          145,
          144,
          143,
          142,
          134,
          133,
          132,
          131,
          130,
          129,
          128,
          127,
          126,
          125,
          124,
          123,
          122,
          121,
          120,
          11,
          10,
          9,
          8,
          "7"
        ],
        "length_m": 863.2110739681666,
        "time_s": 308.2896692743452,
        "efficiency": null,
        "routing_type": "optimal"
      },
      "predicted_delivery_location": [
        -78.36117903300493,
        38.01623618960906
      ]
    },
    {
      "order_id": "021",
      "golfer_group_id": 20,
      "hole_num": 18,
      "placed_hole_num": 12,
      "order_time_s": 22069,
      "queue_delay_s": 2641,
      "prep_time_s": 600,
      "delivery_time_s": 172.14205754613795,
      "return_time_s": 71.42857142857143,
      "total_drive_time_s": 243.5706289747094,
      "delivery_distance_m": 963.9955222583744,
      "total_completion_time_s": 3413.142057546138,
      "delivered_at_time_s": 25482.142057546138,
      "runner_id": "runner_1",
      "order_node_idx": 132,
      "predicted_delivery_node_idx": 211,
      "actual_delivery_node_idx": 211,
      "trip_to_golfer": {
        "nodes": [
          "7",
          232,
          231,
          230,
          229,
          228,
          227,
          226,
          225,
          224,
          223,
          222,
          221,
          220,
          219,
          "218"
        ],
        "length_m": 481.99776112918715,
        "time_s": 172.1420575461383,
        "efficiency": null,
        "routing_type": "optimal"
      },
      "trip_back": {
        "nodes": [
          "218",
          219,
          220,
          221,
          222,
          223,
          224,
          225,
          226,
          227,
          228,
          229,
          230,
          231,
          232,
          "7"
        ],
        "length_m": 481.99776112918727,
        "time_s": 172.14205754613832,
        "efficiency": null,
        "routing_type": "optimal"
      },
      "predicted_delivery_location": [
        -78.36251715362434,
        38.01959227804675
      ]
    },
    {
      "order_id": "022",
      "golfer_group_id": 19,
      "hole_num": 18,
      "placed_hole_num": 14,
      "order_time_s": 22602,
      "queue_delay_s": 2953,
      "prep_time_s": 600,
      "delivery_time_s": 20.18015070227557,
      "return_time_s": 71.42857142857143,
      "total_drive_time_s": 91.608722130847,
      "delivery_distance_m": 113.00884393274998,
      "total_completion_time_s": 3573.1801507022756,
      "delivered_at_time_s": 26175.180150702276,
      "runner_id": "runner_1",
      "order_node_idx": 156,
      "predicted_delivery_node_idx": 225,
      "actual_delivery_node_idx": 232,
      "trip_to_golfer": {
        "nodes": [
          "7",
          232
        ],
        "length_m": 56.50442196637499,
        "time_s": 20.180150702276784,
        "efficiency": null,
        "routing_type": "optimal"
      },
      "trip_back": {
        "nodes": [
          "232",
          7
        ],
        "length_m": 56.50442196637499,
        "time_s": 20.180150702276784,
        "efficiency": null,
        "routing_type": "optimal"
      },
      "predicted_delivery_location": [
        -78.36555477048435,
        38.01729562196628
      ]
    },
    {
      "order_id": "024",
      "golfer_group_id": 30,
      "hole_num": 14,
      "placed_hole_num": 8,
      "order_time_s": 23919,
      "queue_delay_s": 2931,
      "prep_time_s": 600,
      "delivery_time_s": 440.5762077771469,
      "return_time_s": 357.14285714285717,
      "total_drive_time_s": 797.719064920004,
      "delivery_distance_m": 2467.226763552031,
      "total_completion_time_s": 3971.576207777147,
      "delivered_at_time_s": 27890.576207777147,
      "runner_id": "runner_1",
      "order_node_idx": 84,
      "predicted_delivery_node_idx": 162,
      "actual_delivery_node_idx": 161,
      "trip_to_golfer": {
        "nodes": [
          "7",
          8,
          9,
          10,
          11,
          120,
          121,
          122,
          123,
          124,
          125,
          126,
          127,
          128,
          129,
          130,
          131,
          132,
          133,
          134,
          142,
          143,
          144,
          145,
          146,
          147,
          148,
          149,
          150,
          151,
          152,
          153,
          154,
          155,
          175,
          174,
          173,
          172,
          171,
          170,
          "169"
        ],
        "length_m": 1233.6133817760158,
        "time_s": 440.5762077771485,
        "efficiency": null,
        "routing_type": "optimal"
      },
      "trip_back": {
        "nodes": [
          "169",
          170,
          171,
          172,
          173,
          174,
          175,
          155,
          154,
          153,
          152,
          151,
          150,
          149,
          148,
          147,
          146,
          145,
          144,
          143,
          142,
          134,
          133,
          132,
          131,
          130,
          129,
          128,
          127,
          126,
          125,
          124,
          123,
          122,
          121,
          120,
          11,
          10,
          9,
          8,
          "7"
        ],
        "length_m": 1233.6133817760156,
        "time_s": 440.57620777714845,
        "efficiency": null,
        "routing_type": "optimal"
      },
      "predicted_delivery_location": [
        -78.35839372288116,
        38.01426645558792
      ]
    },
    {
      "order_id": "030",
      "golfer_group_id": 21,
      "hole_num": 18,
      "placed_hole_num": 17,
      "order_time_s": 25990,
      "queue_delay_s": 2880,
      "prep_time_s": 600,
      "delivery_time_s": 20.18015070227557,
      "return_time_s": 71.42857142857143,
      "total_drive_time_s": 91.608722130847,
      "delivery_distance_m": 113.00884393274998,
      "total_completion_time_s": 3500.1801507022756,
      "delivered_at_time_s": 29490.180150702276,
      "runner_id": "runner_1",
      "order_node_idx": 192,
      "predicted_delivery_node_idx": 225,
      "actual_delivery_node_idx": 269,
      "trip_to_golfer": {
        "nodes": [
          "7",
          232
        ],
        "length_m": 56.50442196637499,
        "time_s": 20.180150702276784,
        "efficiency": null,
        "routing_type": "optimal"
      },
      "trip_back": {
        "nodes": [
          "232",
          7
        ],
        "length_m": 56.50442196637499,
        "time_s": 20.180150702276784,
        "efficiency": null,
        "routing_type": "optimal"
      },
      "predicted_delivery_location": [
        -78.36555477048435,
        38.01729562196628
      ]
    },
    {
      "order_id": "033",
      "golfer_group_id": 36,
      "hole_num": 14,
      "placed_hole_num": 8,
      "order_time_s": 27400,
      "queue_delay_s": 2770,
      "prep_time_s": 600,
      "delivery_time_s": 440.5762077771469,
      "return_time_s": 357.14285714285717,
      "total_drive_time_s": 797.719064920004,
      "delivery_distance_m": 2467.226763552031,
      "total_completion_time_s": 3810.576207777147,
      "delivered_at_time_s": 31210.576207777147,
      "runner_id": "runner_1",
      "order_node_idx": 84,
      "predicted_delivery_node_idx": 162,
      "actual_delivery_node_idx": 163,
      "trip_to_golfer": {
        "nodes": [
          "7",
          8,
          9,
          10,
          11,
          120,
          121,
          122,
          123,
          124,
          125,
          126,
          127,
          128,
          129,
          130,
          131,
          132,
          133,
          134,
          142,
          143,
          144,
          145,
          146,
          147,
          148,
          149,
          150,
          151,
          152,
          153,
          154,
          155,
          175,
          174,
          173,
          172,
          171,
          170,
          "169"
        ],
        "length_m": 1233.6133817760158,
        "time_s": 440.5762077771485,
        "efficiency": null,
        "routing_type": "optimal"
      },
      "trip_back": {
        "nodes": [
          "169",
          170,
          171,
          172,
          173,
          174,
          175,
          155,
          154,
          153,
          152,
          151,
          150,
          149,
          148,
          147,
          146,
          145,
          144,
          143,
          142,
          134,
          133,
          132,
          131,
          130,
          129,
          128,
          127,
          126,
          125,
          124,
          123,
          122,
          121,
          120,
          11,
          10,
          9,
          8,
          "7"
        ],
        "length_m": 1233.6133817760156,
        "time_s": 440.57620777714845,
        "efficiency": null,
        "routing_type": "optimal"
      },
      "predicted_delivery_location": [
        -78.35839372288116,
        38.01426645558792
      ]
    },
    {
      "order_id": "036",
      "golfer_group_id": 28,
      "hole_num": 18,
      "placed_hole_num": 18,
      "order_time_s": 30495,
      "queue_delay_s": 2275,
      "prep_time_s": 600,
      "delivery_time_s": 20.18015070227557,
      "return_time_s": 71.42857142857143,
      "total_drive_time_s": 91.608722130847,
      "delivery_distance_m": 113.00884393274998,
      "total_completion_time_s": 2895.1801507022756,
      "delivered_at_time_s": 33390.180150702276,
      "runner_id": "runner_1",
      "order_node_idx": 204,
      "predicted_delivery_node_idx": 225,
      "actual_delivery_node_idx": 271,
      "trip_to_golfer": {
        "nodes": [
          "7",
          232
        ],
        "length_m": 56.50442196637499,
        "time_s": 20.180150702276784,
        "efficiency": null,
        "routing_type": "optimal"
      },
      "trip_back": {
        "nodes": [
          "232",
          7
        ],
        "length_m": 56.50442196637499,
        "time_s": 20.180150702276784,
        "efficiency": null,
        "routing_type": "optimal"
      },
      "predicted_delivery_location": [
        -78.36555477048435,
        38.01729562196628
      ]
    },
    {
      "order_id": "037",
      "golfer_group_id": 29,
      "hole_num": 18,
      "placed_hole_num": 18,
      "order_time_s": 31076,
      "queue_delay_s": 2389,
      "prep_time_s": 600,
      "delivery_time_s": 20.18015070227557,
      "return_time_s": 71.42857142857143,
      "total_drive_time_s": 91.608722130847,
      "delivery_distance_m": 113.00884393274998,
      "total_completion_time_s": 3009.1801507022756,
      "delivered_at_time_s": 34085.180150702276,
      "runner_id": "runner_1",
      "order_node_idx": 204,
      "predicted_delivery_node_idx": 225,
      "actual_delivery_node_idx": 274,
      "trip_to_golfer": {
        "nodes": [
          "7",
          232
        ],
        "length_m": 56.50442196637499,
        "time_s": 20.180150702276784,
        "efficiency": null,
        "routing_type": "optimal"
      },
      "trip_back": {
        "nodes": [
          "232",
          7
        ],
        "length_m": 56.50442196637499,
        "time_s": 20.180150702276784,
        "efficiency": null,
        "routing_type": "optimal"
      },
      "predicted_delivery_location": [
        -78.36555477048435,
        38.01729562196628
      ]
    },
    {
      "order_id": "038",
      "golfer_group_id": 39,
      "hole_num": 17,
      "placed_hole_num": 14,
      "order_time_s": 33040,
      "queue_delay_s": 1120,
      "prep_time_s": 600,
      "delivery_time_s": 293.7253619356925,
      "return_time_s": 142.85714285714286,
      "total_drive_time_s": 436.5825047928354,
      "delivery_distance_m": 1644.8620268398765,
      "total_completion_time_s": 2013.7253619356925,
      "delivered_at_time_s": 35053.72536193569,
      "runner_id": "runner_1",
      "order_node_idx": 156,
      "predicted_delivery_node_idx": 200,
      "actual_delivery_node_idx": 200,
      "trip_to_golfer": {
        "nodes": [
          "7",
          232,
          231,
          230,
          229,
          228,
          227,
          226,
          225,
          224,
          223,
          222,
          221,
          220,
          219,
          218,
          217,
          216,
          215,
          214,
          213,
          212,
          211,
          210,
          209,
          208,
          "207"
        ],
        "length_m": 822.4310134199384,
        "time_s": 293.7253619356923,
        "efficiency": null,
        "routing_type": "optimal"
      },
      "trip_back": {
        "nodes": [
          "207",
          208,
          209,
          210,
          211,
          212,
          213,
          214,
          215,
          216,
          217,
          218,
          219,
          220,
          221,
          222,
          223,
          224,
          225,
          226,
          227,
          228,
          229,
          230,
          231,
          232,
          "7"
        ],
        "length_m": 822.4310134199382,
        "time_s": 293.7253619356922,
        "efficiency": null,
        "routing_type": "optimal"
      },
      "predicted_delivery_location": [
        -78.35865309064599,
        38.01944252547635
      ]
    },
    {
      "order_id": "039",
      "golfer_group_id": 48,
      "hole_num": 12,
      "placed_hole_num": 7,
      "order_time_s": 33235,
      "queue_delay_s": 1965,
      "prep_time_s": 600,
      "delivery_time_s": 220.07264143461362,
      "return_time_s": 500.00000000000006,
      "total_drive_time_s": 720.0726414346136,
      "delivery_distance_m": 1232.4067920338525,
      "total_completion_time_s": 2785.0726414346136,
      "delivered_at_time_s": 36020.07264143461,
      "runner_id": "runner_1",
      "order_node_idx": 72,
      "predicted_delivery_node_idx": 135,
      "actual_delivery_node_idx": 135,
      "trip_to_golfer": {
        "nodes": [
          "7",
          8,
          9,
          10,
          11,
          120,
          121,
          122,
          123,
          124,
          125,
          126,
          127,
          128,
          129,
          130,
          131,
          132,
          133,
          134,
          "142"
        ],
        "length_m": 616.2033960169264,
        "time_s": 220.07264143461657,
        "efficiency": null,
        "routing_type": "optimal"
      },
      "trip_back": {
        "nodes": [
          "142",
          134,
          133,
          132,
          131,
          130,
          129,
          128,
          127,
          126,
          125,
          124,
          123,
          122,
          121,
          120,
          11,
          10,
          9,
          8,
          "7"
        ],
        "length_m": 616.2033960169263,
        "time_s": 220.07264143461654,
        "efficiency": null,
        "routing_type": "optimal"
      },
      "predicted_delivery_location": [
        -78.3617903429719,
        38.01833936831649
      ]
    },
    {
      "order_id": "042",
      "golfer_group_id": 50,
      "hole_num": 14,
      "placed_hole_num": 9,
      "order_time_s": 35650,
      "queue_delay_s": 2075,
      "prep_time_s": 600,
      "delivery_time_s": 440.57620777715056,
      "return_time_s": 357.14285714285717,
      "total_drive_time_s": 797.7190649200077,
      "delivery_distance_m": 2467.226763552031,
      "total_completion_time_s": 3115.5762077771506,
      "delivered_at_time_s": 38765.57620777715,
      "runner_id": "runner_1",
      "order_node_idx": 96,
      "predicted_delivery_node_idx": 162,
      "actual_delivery_node_idx": 163,
      "trip_to_golfer": {
        "nodes": [
          "7",
          8,
          9,
          10,
          11,
          120,
          121,
          122,
          123,
          124,
          125,
          126,
          127,
          128,
          129,
          130,
          131,
          132,
          133,
          134,
          142,
          143,
          144,
          145,
          146,
          147,
          148,
          149,
          150,
          151,
          152,
          153,
          154,
          155,
          175,
          174,
          173,
          172,
          171,
          170,
          "169"
        ],
        "length_m": 1233.6133817760158,
        "time_s": 440.5762077771485,
        "efficiency": null,
        "routing_type": "optimal"
      },
      "trip_back": {
        "nodes": [
          "169",
          170,
          171,
          172,
          173,
          174,
          175,
          155,
          154,
          153,
          152,
          151,
          150,
          149,
          148,
          147,
          146,
          145,
          144,
          143,
          142,
          134,
          133,
          132,
          131,
          130,
          129,
          128,
          127,
          126,
          125,
          124,
          123,
          122,
          121,
          120,
          11,
          10,
          9,
          8,
          "7"
        ],
        "length_m": 1233.6133817760156,
        "time_s": 440.57620777714845,
        "efficiency": null,
        "routing_type": "optimal"
      },
      "predicted_delivery_location": [
        -78.35839372288116,
        38.01426645558792
      ]
    }
  ],
  "failed_orders": [
    {
      "order_id": "004",
      "reason": "Not dispatched within 60 minutes"
    },
    {
      "order_id": "005",
      "reason": "Not dispatched within 60 minutes"
    },
    {
      "order_id": "006",
      "reason": "Not dispatched within 60 minutes"
    },
    {
      "order_id": "007",
      "reason": "Not dispatched within 60 minutes"
    },
    {
      "order_id": "008",
      "reason": "Not dispatched within 60 minutes"
    },
    {
      "order_id": "009",
      "reason": "Not dispatched within 60 minutes"
    },
    {
      "order_id": "010",
      "reason": "Not dispatched within 60 minutes"
    },
    {
      "order_id": "011",
      "reason": "Not dispatched within 60 minutes"
    },
    {
      "order_id": "012",
      "reason": "Not dispatched within 60 minutes"
    },
    {
      "order_id": "013",
      "reason": "Not dispatched within 60 minutes"
    },
    {
      "order_id": "014",
      "reason": "Not dispatched within 60 minutes"
    },
    {
      "order_id": "015",
      "reason": "Not dispatched within 60 minutes"
    },
    {
      "order_id": "016",
      "reason": "Not dispatched within 60 minutes"
    },
    {
      "order_id": "017",
      "reason": "Not dispatched within 60 minutes"
    },
    {
      "order_id": "018",
      "reason": "Not dispatched within 60 minutes"
    },
    {
      "order_id": "019",
      "reason": "Not dispatched within 60 minutes"
    },
    {
      "order_id": "020",
      "reason": "Not dispatched within 60 minutes"
    },
    {
      "order_id": "023",
      "reason": "Not dispatched within 60 minutes"
    },
    {
      "order_id": "025",
      "reason": "Not dispatched within 60 minutes"
    },
    {
      "order_id": "026",
      "reason": "Not dispatched within 60 minutes"
    },
    {
      "order_id": "027",
      "reason": "Not dispatched within 60 minutes"
    },
    {
      "order_id": "028",
      "reason": "Not dispatched within 60 minutes"
    },
    {
      "order_id": "029",
      "reason": "Not dispatched within 60 minutes"
    },
    {
      "order_id": "031",
      "reason": "Not dispatched within 60 minutes"
    },
    {
      "order_id": "032",
      "reason": "Not dispatched within 60 minutes"
    },
    {
      "order_id": "034",
      "reason": "Not dispatched within 60 minutes"
    },
    {
      "order_id": "035",
      "reason": "Not dispatched within 60 minutes"
    },
    {
      "order_id": "040",
      "reason": "Not dispatched within 60 minutes"
    },
    {
      "order_id": "041",
      "reason": "Not dispatched within 60 minutes"
    },
    {
      "order_id": "043",
      "reason": "Not dispatched within 60 minutes"
    }
  ],
  "activity_log": [
    {
      "timestamp_s": 0,
      "time_str": "07:00",
      "activity_type": "service_closed",
      "description": "runner_1 waiting 240 minutes until opening",
      "order_id": null,
      "location": "clubhouse",
      "runner_id": "runner_1"
    },
    {
      "timestamp_s": 14400,
      "time_str": "11:00",
      "activity_type": "service_opened",
      "description": "runner_1 started shift",
      "order_id": null,
      "location": "clubhouse",
      "runner_id": "runner_1"
    },
    {
      "timestamp_s": 14435,
      "time_str": "11:00",
      "activity_type": "order_assigned",
      "description": "Assigned Order 001 to runner_1",
      "order_id": "001",
      "location": "clubhouse",
      "runner_id": "runner_1"
    },
    {
      "timestamp_s": 14435,
      "time_str": "11:00",
      "activity_type": "prep_start",
      "description": "runner_1 started prep for Order 001 (Hole 11)",
      "order_id": "001",
      "location": "clubhouse",
      "runner_id": "runner_1"
    },
    {
      "timestamp_s": 15035,
      "time_str": "11:10",
      "activity_type": "prep_complete",
      "description": "runner_1 completed prep for Order 001",
      "order_id": "001",
      "location": "clubhouse",
      "runner_id": "runner_1"
    },
    {
      "timestamp_s": 15035,
      "time_str": "11:10",
      "activity_type": "delivery_start",
      "description": "runner_1 departing to Hole 13 (2583m, 7.7 min)",
      "order_id": "001",
      "location": "clubhouse",
      "runner_id": "runner_1"
    },
    {
      "timestamp_s": 15496.177092111848,
      "time_str": "11:18",
      "activity_type": "delivery_complete",
      "description": "runner_1 delivered Order 001 to Hole 13 (Total completion: 17.7 min)",
      "order_id": "001",
      "location": "hole_13",
      "runner_id": "runner_1"
    },
    {
      "timestamp_s": 15496.177092111848,
      "time_str": "11:18",
      "activity_type": "returning",
      "description": "runner_1 returning to clubhouse from hole_13 (7.1 min)",
      "order_id": "001",
      "location": "hole_13",
      "runner_id": "runner_1"
    },
    {
      "timestamp_s": 15924.748520683277,
      "time_str": "11:25",
      "activity_type": "arrived_clubhouse",
      "description": "runner_1 arrived at clubhouse after delivering Order 001",
      "order_id": "001",
      "location": "clubhouse",
      "runner_id": "runner_1"
    },
    {
      "timestamp_s": 15925,
      "time_str": "11:25",
      "activity_type": "order_assigned",
      "description": "Assigned Order 002 to runner_1",
      "order_id": "002",
      "location": "clubhouse",
      "runner_id": "runner_1"
    },
    {
      "timestamp_s": 15925,
      "time_str": "11:25",
      "activity_type": "prep_start",
      "description": "runner_1 started prep for Order 002 (Hole 6)",
      "order_id": "002",
      "location": "clubhouse",
      "runner_id": "runner_1"
    },
    {
      "timestamp_s": 16525,
      "time_str": "11:35",
      "activity_type": "prep_complete",
      "description": "runner_1 completed prep for Order 002",
      "order_id": "002",
      "location": "clubhouse",
      "runner_id": "runner_1"
    },
    {
      "timestamp_s": 16525,
      "time_str": "11:35",
      "activity_type": "delivery_start",
      "description": "runner_1 departing to Hole 10 (524m, 1.6 min)",
      "order_id": "002",
      "location": "clubhouse",
      "runner_id": "runner_1"
    },
    {
      "timestamp_s": 16618.63742399374,
      "time_str": "11:36",
      "activity_type": "delivery_complete",
      "description": "runner_1 delivered Order 002 to Hole 10 (Total completion: 34.8 min)",
      "order_id": "002",
      "location": "hole_10",
      "runner_id": "runner_1"
    },
    {
      "timestamp_s": 16618.63742399374,
      "time_str": "11:36",
      "activity_type": "returning",
      "description": "runner_1 returning to clubhouse from hole_10 (10.7 min)",
      "order_id": "002",
      "location": "hole_10",
      "runner_id": "runner_1"
    },
    {
      "timestamp_s": 17261.49456685088,
      "time_str": "11:47",
      "activity_type": "arrived_clubhouse",
      "description": "runner_1 arrived at clubhouse after delivering Order 002",
      "order_id": "002",
      "location": "clubhouse",
      "runner_id": "runner_1"
    },
    {
      "timestamp_s": 17265,
      "time_str": "11:47",
      "activity_type": "order_assigned",
      "description": "Assigned Order 003 to runner_1",
      "order_id": "003",
      "location": "clubhouse",
      "runner_id": "runner_1"
    },
    {
      "timestamp_s": 17265,
      "time_str": "11:47",
      "activity_type": "prep_start",
      "description": "runner_1 started prep for Order 003 (Hole 7)",
      "order_id": "003",
      "location": "clubhouse",
      "runner_id": "runner_1"
    },
    {
      "timestamp_s": 17865,
      "time_str": "11:57",
      "activity_type": "prep_complete",
      "description": "runner_1 completed prep for Order 003",
      "order_id": "003",
      "location": "clubhouse",
      "runner_id": "runner_1"
    },
    {
      "timestamp_s": 17865,
      "time_str": "11:57",
      "activity_type": "delivery_start",
      "description": "runner_1 departing to Hole 12 (1726m, 5.1 min)",
      "order_id": "003",
      "location": "clubhouse",
      "runner_id": "runner_1"
    },
    {
      "timestamp_s": 18173.289669274345,
      "time_str": "12:02",
      "activity_type": "delivery_complete",
      "description": "runner_1 delivered Order 003 to Hole 12 (Total completion: 56.4 min)",
      "order_id": "003",
      "location": "hole_12",
      "runner_id": "runner_1"
    },
    {
      "timestamp_s": 18173.289669274345,
      "time_str": "12:02",
      "activity_type": "returning",
      "description": "runner_1 returning to clubhouse from hole_12 (8.3 min)",
      "order_id": "003",
      "location": "hole_12",
      "runner_id": "runner_1"
    },
    {
      "timestamp_s": 18673.289669274345,
      "time_str": "12:11",
      "activity_type": "arrived_clubhouse",
      "description": "runner_1 arrived at clubhouse after delivering Order 003",
      "order_id": "003",
      "location": "clubhouse",
      "runner_id": "runner_1"
    },
    {
      "timestamp_s": 18675,
      "time_str": "12:11",
      "activity_type": "order_assigned",
      "description": "Assigned Order 004 to runner_1",
      "order_id": "004",
      "location": "clubhouse",
      "runner_id": "runner_1"
    },
    {
      "timestamp_s": 18675,
      "time_str": "12:11",
      "activity_type": "prep_start",
      "description": "runner_1 started prep for Order 004 (Hole 9)",
      "order_id": "004",
      "location": "clubhouse",
      "runner_id": "runner_1"
    },
    {
      "timestamp_s": 19275,
      "time_str": "12:21",
      "activity_type": "prep_complete",
      "description": "runner_1 completed prep for Order 004",
      "order_id": "004",
      "location": "clubhouse",
      "runner_id": "runner_1"
    },
    {
      "timestamp_s": 19275,
      "time_str": "12:21",
      "activity_type": "order_failed_timeout",
      "description": "runner_1 exceeded timeout before departure for Order 004; discarding",
      "order_id": "004",
      "location": "clubhouse",
      "runner_id": "runner_1"
    },
    {
      "timestamp_s": 19275,
      "time_str": "12:21",
      "activity_type": "order_assigned",
      "description": "Assigned Order 005 to runner_1",
      "order_id": "005",
      "location": "clubhouse",
      "runner_id": "runner_1"
    },
    {
      "timestamp_s": 19275,
      "time_str": "12:21",
      "activity_type": "prep_start",
      "description": "runner_1 started prep for Order 005 (Hole 17)",
      "order_id": "005",
      "location": "clubhouse",
      "runner_id": "runner_1"
    },
    {
      "timestamp_s": 19875,
      "time_str": "12:31",
      "activity_type": "prep_complete",
      "description": "runner_1 completed prep for Order 005",
      "order_id": "005",
      "location": "clubhouse",
      "runner_id": "runner_1"
    },
    {
      "timestamp_s": 19875,
      "time_str": "12:31",
      "activity_type": "order_failed_timeout",
      "description": "runner_1 exceeded timeout before departure for Order 005; discarding",
      "order_id": "005",
      "location": "clubhouse",
      "runner_id": "runner_1"
    },
    {
      "timestamp_s": 19875,
      "time_str": "12:31",
      "activity_type": "order_assigned",
      "description": "Assigned Order 006 to runner_1",
      "order_id": "006",
      "location": "clubhouse",
      "runner_id": "runner_1"
    },
    {
      "timestamp_s": 19875,
      "time_str": "12:31",
      "activity_type": "order_failed_timeout",
      "description": "runner_1 received expired order 006; discarding",
      "order_id": "006",
      "location": "clubhouse",
      "runner_id": "runner_1"
    },
    {
      "timestamp_s": 19880,
      "time_str": "12:31",
      "activity_type": "order_assigned",
      "description": "Assigned Order 007 to runner_1",
      "order_id": "007",
      "location": "clubhouse",
      "runner_id": "runner_1"
    },
    {
      "timestamp_s": 19880,
      "time_str": "12:31",
      "activity_type": "prep_start",
      "description": "runner_1 started prep for Order 007 (Hole 17)",
      "order_id": "007",
      "location": "clubhouse",
      "runner_id": "runner_1"
    },
    {
      "timestamp_s": 20480,
      "time_str": "12:41",
      "activity_type": "prep_complete",
      "description": "runner_1 completed prep for Order 007",
      "order_id": "007",
      "location": "clubhouse",
      "runner_id": "runner_1"
    },
    {
      "timestamp_s": 20480,
      "time_str": "12:41",
      "activity_type": "order_failed_timeout",
      "description": "runner_1 exceeded timeout before departure for Order 007; discarding",
      "order_id": "007",
      "location": "clubhouse",
      "runner_id": "runner_1"
    },
    {
      "timestamp_s": 20480,
      "time_str": "12:41",
      "activity_type": "order_assigned",
      "description": "Assigned Order 008 to runner_1",
      "order_id": "008",
      "location": "clubhouse",
      "runner_id": "runner_1"
    },
    {
      "timestamp_s": 20480,
      "time_str": "12:41",
      "activity_type": "prep_start",
      "description": "runner_1 started prep for Order 008 (Hole 15)",
      "order_id": "008",
      "location": "clubhouse",
      "runner_id": "runner_1"
    },
    {
      "timestamp_s": 21080,
      "time_str": "12:51",
      "activity_type": "prep_complete",
      "description": "runner_1 completed prep for Order 008",
      "order_id": "008",
      "location": "clubhouse",
      "runner_id": "runner_1"
    },
    {
      "timestamp_s": 21080,
      "time_str": "12:51",
      "activity_type": "order_failed_timeout",
      "description": "runner_1 exceeded timeout before departure for Order 008; discarding",
      "order_id": "008",
      "location": "clubhouse",
      "runner_id": "runner_1"
    },
    {
      "timestamp_s": 21080,
      "time_str": "12:51",
      "activity_type": "order_assigned",
      "description": "Assigned Order 009 to runner_1",
      "order_id": "009",
      "location": "clubhouse",
      "runner_id": "runner_1"
    },
    {
      "timestamp_s": 21080,
      "time_str": "12:51",
      "activity_type": "prep_start",
      "description": "runner_1 started prep for Order 009 (Hole 14)",
      "order_id": "009",
      "location": "clubhouse",
      "runner_id": "runner_1"
    },
    {
      "timestamp_s": 21680,
      "time_str": "13:01",
      "activity_type": "prep_complete",
      "description": "runner_1 completed prep for Order 009",
      "order_id": "009",
      "location": "clubhouse",
      "runner_id": "runner_1"
    },
    {
      "timestamp_s": 21680,
      "time_str": "13:01",
      "activity_type": "order_failed_timeout",
      "description": "runner_1 exceeded timeout before departure for Order 009; discarding",
      "order_id": "009",
      "location": "clubhouse",
      "runner_id": "runner_1"
    },
    {
      "timestamp_s": 21680,
      "time_str": "13:01",
      "activity_type": "order_assigned",
      "description": "Assigned Order 010 to runner_1",
      "order_id": "010",
      "location": "clubhouse",
      "runner_id": "runner_1"
    },
    {
      "timestamp_s": 21680,
      "time_str": "13:01",
      "activity_type": "prep_start",
      "description": "runner_1 started prep for Order 010 (Hole 16)",
      "order_id": "010",
      "location": "clubhouse",
      "runner_id": "runner_1"
    },
    {
      "timestamp_s": 22280,
      "time_str": "13:11",
      "activity_type": "prep_complete",
      "description": "runner_1 completed prep for Order 010",
      "order_id": "010",
      "location": "clubhouse",
      "runner_id": "runner_1"
    },
    {
      "timestamp_s": 22280,
      "time_str": "13:11",
      "activity_type": "order_failed_timeout",
      "description": "runner_1 exceeded timeout before departure for Order 010; discarding",
      "order_id": "010",
      "location": "clubhouse",
      "runner_id": "runner_1"
    },
    {
      "timestamp_s": 22280,
      "time_str": "13:11",
      "activity_type": "order_assigned",
      "description": "Assigned Order 011 to runner_1",
      "order_id": "011",
      "location": "clubhouse",
      "runner_id": "runner_1"
    },
    {
      "timestamp_s": 22280,
      "time_str": "13:11",
      "activity_type": "prep_start",
      "description": "runner_1 started prep for Order 011 (Hole 17)",
      "order_id": "011",
      "location": "clubhouse",
      "runner_id": "runner_1"
    },
    {
      "timestamp_s": 22880,
      "time_str": "13:21",
      "activity_type": "prep_complete",
      "description": "runner_1 completed prep for Order 011",
      "order_id": "011",
      "location": "clubhouse",
      "runner_id": "runner_1"
    },
    {
      "timestamp_s": 22880,
      "time_str": "13:21",
      "activity_type": "order_failed_timeout",
      "description": "runner_1 exceeded timeout before departure for Order 011; discarding",
      "order_id": "011",
      "location": "clubhouse",
      "runner_id": "runner_1"
    },
    {
      "timestamp_s": 22880,
      "time_str": "13:21",
      "activity_type": "order_assigned",
      "description": "Assigned Order 012 to runner_1",
      "order_id": "012",
      "location": "clubhouse",
      "runner_id": "runner_1"
    },
    {
      "timestamp_s": 22880,
      "time_str": "13:21",
      "activity_type": "order_failed_timeout",
      "description": "runner_1 received expired order 012; discarding",
      "order_id": "012",
      "location": "clubhouse",
      "runner_id": "runner_1"
    },
    {
      "timestamp_s": 22885,
      "time_str": "13:21",
      "activity_type": "order_assigned",
      "description": "Assigned Order 013 to runner_1",
      "order_id": "013",
      "location": "clubhouse",
      "runner_id": "runner_1"
    },
    {
      "timestamp_s": 22885,
      "time_str": "13:21",
      "activity_type": "order_failed_timeout",
      "description": "runner_1 received expired order 013; discarding",
      "order_id": "013",
      "location": "clubhouse",
      "runner_id": "runner_1"
    },
    {
      "timestamp_s": 22890,
      "time_str": "13:21",
      "activity_type": "order_assigned",
      "description": "Assigned Order 014 to runner_1",
      "order_id": "014",
      "location": "clubhouse",
      "runner_id": "runner_1"
    },
    {
      "timestamp_s": 22890,
      "time_str": "13:21",
      "activity_type": "prep_start",
      "description": "runner_1 started prep for Order 014 (Hole 9)",
      "order_id": "014",
      "location": "clubhouse",
      "runner_id": "runner_1"
    },
    {
      "timestamp_s": 23490,
      "time_str": "13:31",
      "activity_type": "prep_complete",
      "description": "runner_1 completed prep for Order 014",
      "order_id": "014",
      "location": "clubhouse",
      "runner_id": "runner_1"
    },
    {
      "timestamp_s": 23490,
      "time_str": "13:31",
      "activity_type": "order_failed_timeout",
      "description": "runner_1 exceeded timeout before departure for Order 014; discarding",
      "order_id": "014",
      "location": "clubhouse",
      "runner_id": "runner_1"
    },
    {
      "timestamp_s": 23490,
      "time_str": "13:31",
      "activity_type": "order_assigned",
      "description": "Assigned Order 015 to runner_1",
      "order_id": "015",
      "location": "clubhouse",
      "runner_id": "runner_1"
    },
    {
      "timestamp_s": 23490,
      "time_str": "13:31",
      "activity_type": "prep_start",
      "description": "runner_1 started prep for Order 015 (Hole 17)",
      "order_id": "015",
      "location": "clubhouse",
      "runner_id": "runner_1"
    },
    {
      "timestamp_s": 24090,
      "time_str": "13:41",
      "activity_type": "prep_complete",
      "description": "runner_1 completed prep for Order 015",
      "order_id": "015",
      "location": "clubhouse",
      "runner_id": "runner_1"
    },
    {
      "timestamp_s": 24090,
      "time_str": "13:41",
      "activity_type": "order_failed_timeout",
      "description": "runner_1 exceeded timeout before departure for Order 015; discarding",
      "order_id": "015",
      "location": "clubhouse",
      "runner_id": "runner_1"
    },
    {
      "timestamp_s": 24090,
      "time_str": "13:41",
      "activity_type": "order_assigned",
      "description": "Assigned Order 016 to runner_1",
      "order_id": "016",
      "location": "clubhouse",
      "runner_id": "runner_1"
    },
    {
      "timestamp_s": 24090,
      "time_str": "13:41",
      "activity_type": "order_failed_timeout",
      "description": "runner_1 received expired order 016; discarding",
      "order_id": "016",
      "location": "clubhouse",
      "runner_id": "runner_1"
    },
    {
      "timestamp_s": 24095,
      "time_str": "13:41",
      "activity_type": "order_assigned",
      "description": "Assigned Order 017 to runner_1",
      "order_id": "017",
      "location": "clubhouse",
      "runner_id": "runner_1"
    },
    {
      "timestamp_s": 24095,
      "time_str": "13:41",
      "activity_type": "order_failed_timeout",
      "description": "runner_1 received expired order 017; discarding",
      "order_id": "017",
      "location": "clubhouse",
      "runner_id": "runner_1"
    },
    {
      "timestamp_s": 24100,
      "time_str": "13:41",
      "activity_type": "order_assigned",
      "description": "Assigned Order 018 to runner_1",
      "order_id": "018",
      "location": "clubhouse",
      "runner_id": "runner_1"
    },
    {
      "timestamp_s": 24100,
      "time_str": "13:41",
      "activity_type": "prep_start",
      "description": "runner_1 started prep for Order 018 (Hole 15)",
      "order_id": "018",
      "location": "clubhouse",
      "runner_id": "runner_1"
    },
    {
      "timestamp_s": 24700,
      "time_str": "13:51",
      "activity_type": "prep_complete",
      "description": "runner_1 completed prep for Order 018",
      "order_id": "018",
      "location": "clubhouse",
      "runner_id": "runner_1"
    },
    {
      "timestamp_s": 24700,
      "time_str": "13:51",
      "activity_type": "order_failed_timeout",
      "description": "runner_1 exceeded timeout before departure for Order 018; discarding",
      "order_id": "018",
      "location": "clubhouse",
      "runner_id": "runner_1"
    },
    {
      "timestamp_s": 24700,
      "time_str": "13:51",
      "activity_type": "order_assigned",
      "description": "Assigned Order 019 to runner_1",
      "order_id": "019",
      "location": "clubhouse",
      "runner_id": "runner_1"
    },
    {
      "timestamp_s": 24700,
      "time_str": "13:51",
      "activity_type": "order_failed_timeout",
      "description": "runner_1 received expired order 019; discarding",
      "order_id": "019",
      "location": "clubhouse",
      "runner_id": "runner_1"
    },
    {
      "timestamp_s": 24705,
      "time_str": "13:51",
      "activity_type": "order_assigned",
      "description": "Assigned Order 020 to runner_1",
      "order_id": "020",
      "location": "clubhouse",
      "runner_id": "runner_1"
    },
    {
      "timestamp_s": 24705,
      "time_str": "13:51",
      "activity_type": "order_failed_timeout",
      "description": "runner_1 received expired order 020; discarding",
      "order_id": "020",
      "location": "clubhouse",
      "runner_id": "runner_1"
    },
    {
      "timestamp_s": 24710,
      "time_str": "13:51",
      "activity_type": "order_assigned",
      "description": "Assigned Order 021 to runner_1",
      "order_id": "021",
      "location": "clubhouse",
      "runner_id": "runner_1"
    },
    {
      "timestamp_s": 24710,
      "time_str": "13:51",
      "activity_type": "prep_start",
      "description": "runner_1 started prep for Order 021 (Hole 12)",
      "order_id": "021",
      "location": "clubhouse",
      "runner_id": "runner_1"
    },
    {
      "timestamp_s": 25310,
      "time_str": "14:01",
      "activity_type": "prep_complete",
      "description": "runner_1 completed prep for Order 021",
      "order_id": "021",
      "location": "clubhouse",
      "runner_id": "runner_1"
    },
    {
      "timestamp_s": 25310,
      "time_str": "14:01",
      "activity_type": "delivery_start",
      "description": "runner_1 departing to Hole 18 (964m, 2.9 min)",
      "order_id": "021",
      "location": "clubhouse",
      "runner_id": "runner_1"
    },
    {
      "timestamp_s": 25482.142057546138,
      "time_str": "14:04",
      "activity_type": "delivery_complete",
      "description": "runner_1 delivered Order 021 to Hole 18 (Total completion: 56.9 min)",
      "order_id": "021",
      "location": "hole_18",
      "runner_id": "runner_1"
    },
    {
      "timestamp_s": 25482.142057546138,
      "time_str": "14:04",
      "activity_type": "returning",
      "description": "runner_1 returning to clubhouse from hole_18 (1.2 min)",
      "order_id": "021",
      "location": "hole_18",
      "runner_id": "runner_1"
    },
    {
      "timestamp_s": 25553.57062897471,
      "time_str": "14:05",
      "activity_type": "arrived_clubhouse",
      "description": "runner_1 arrived at clubhouse after delivering Order 021",
      "order_id": "021",
      "location": "clubhouse",
      "runner_id": "runner_1"
    },
    {
      "timestamp_s": 25555,
      "time_str": "14:05",
      "activity_type": "order_assigned",
      "description": "Assigned Order 022 to runner_1",
      "order_id": "022",
      "location": "clubhouse",
      "runner_id": "runner_1"
    },
    {
      "timestamp_s": 25555,
      "time_str": "14:05",
      "activity_type": "prep_start",
      "description": "runner_1 started prep for Order 022 (Hole 14)",
      "order_id": "022",
      "location": "clubhouse",
      "runner_id": "runner_1"
    },
    {
      "timestamp_s": 26155,
      "time_str": "14:15",
      "activity_type": "prep_complete",
      "description": "runner_1 completed prep for Order 022",
      "order_id": "022",
      "location": "clubhouse",
      "runner_id": "runner_1"
    },
    {
      "timestamp_s": 26155,
      "time_str": "14:15",
      "activity_type": "delivery_start",
      "description": "runner_1 departing to Hole 18 (113m, 0.3 min)",
      "order_id": "022",
      "location": "clubhouse",
      "runner_id": "runner_1"
    },
    {
      "timestamp_s": 26175.180150702276,
      "time_str": "14:16",
      "activity_type": "delivery_complete",
      "description": "runner_1 delivered Order 022 to Hole 18 (Total completion: 59.6 min)",
      "order_id": "022",
      "location": "hole_18",
      "runner_id": "runner_1"
    },
    {
      "timestamp_s": 26175.180150702276,
      "time_str": "14:16",
      "activity_type": "returning",
      "description": "runner_1 returning to clubhouse from hole_18 (1.2 min)",
      "order_id": "022",
      "location": "hole_18",
      "runner_id": "runner_1"
    },
    {
      "timestamp_s": 26246.608722130848,
      "time_str": "14:17",
      "activity_type": "arrived_clubhouse",
      "description": "runner_1 arrived at clubhouse after delivering Order 022",
      "order_id": "022",
      "location": "clubhouse",
      "runner_id": "runner_1"
    },
    {
      "timestamp_s": 26250,
      "time_str": "14:17",
      "activity_type": "order_assigned",
      "description": "Assigned Order 023 to runner_1",
      "order_id": "023",
      "location": "clubhouse",
      "runner_id": "runner_1"
    },
    {
      "timestamp_s": 26250,
      "time_str": "14:17",
      "activity_type": "prep_start",
      "description": "runner_1 started prep for Order 023 (Hole 8)",
      "order_id": "023",
      "location": "clubhouse",
      "runner_id": "runner_1"
    },
    {
      "timestamp_s": 26850,
      "time_str": "14:27",
      "activity_type": "prep_complete",
      "description": "runner_1 completed prep for Order 023",
      "order_id": "023",
      "location": "clubhouse",
      "runner_id": "runner_1"
    },
    {
      "timestamp_s": 26850,
      "time_str": "14:27",
      "activity_type": "order_failed_timeout",
      "description": "runner_1 exceeded timeout before departure for Order 023; discarding",
      "order_id": "023",
      "location": "clubhouse",
      "runner_id": "runner_1"
    },
    {
      "timestamp_s": 26850,
      "time_str": "14:27",
      "activity_type": "order_assigned",
      "description": "Assigned Order 024 to runner_1",
      "order_id": "024",
      "location": "clubhouse",
      "runner_id": "runner_1"
    },
    {
      "timestamp_s": 26850,
      "time_str": "14:27",
      "activity_type": "prep_start",
      "description": "runner_1 started prep for Order 024 (Hole 8)",
      "order_id": "024",
      "location": "clubhouse",
      "runner_id": "runner_1"
    },
    {
      "timestamp_s": 27450,
      "time_str": "14:37",
      "activity_type": "prep_complete",
      "description": "runner_1 completed prep for Order 024",
      "order_id": "024",
      "location": "clubhouse",
      "runner_id": "runner_1"
    },
    {
      "timestamp_s": 27450,
      "time_str": "14:37",
      "activity_type": "delivery_start",
      "description": "runner_1 departing to Hole 14 (2467m, 7.3 min)",
      "order_id": "024",
      "location": "clubhouse",
      "runner_id": "runner_1"
    },
    {
      "timestamp_s": 27890.576207777147,
      "time_str": "14:44",
      "activity_type": "delivery_complete",
      "description": "runner_1 delivered Order 024 to Hole 14 (Total completion: 66.2 min)",
      "order_id": "024",
      "location": "hole_14",
      "runner_id": "runner_1"
    },
    {
      "timestamp_s": 27890.576207777147,
      "time_str": "14:44",
      "activity_type": "returning",
      "description": "runner_1 returning to clubhouse from hole_14 (6.0 min)",
      "order_id": "024",
      "location": "hole_14",
      "runner_id": "runner_1"
    },
    {
      "timestamp_s": 28247.719064920006,
      "time_str": "14:50",
      "activity_type": "arrived_clubhouse",
      "description": "runner_1 arrived at clubhouse after delivering Order 024",
      "order_id": "024",
      "location": "clubhouse",
      "runner_id": "runner_1"
    },
    {
      "timestamp_s": 28250,
      "time_str": "14:50",
      "activity_type": "order_assigned",
      "description": "Assigned Order 025 to runner_1",
      "order_id": "025",
      "location": "clubhouse",
      "runner_id": "runner_1"
    },
    {
      "timestamp_s": 28250,
      "time_str": "14:50",
      "activity_type": "order_failed_timeout",
      "description": "runner_1 received expired order 025; discarding",
      "order_id": "025",
      "location": "clubhouse",
      "runner_id": "runner_1"
    },
    {
      "timestamp_s": 28255,
      "time_str": "14:50",
      "activity_type": "order_assigned",
      "description": "Assigned Order 026 to runner_1",
      "order_id": "026",
      "location": "clubhouse",
      "runner_id": "runner_1"
    },
    {
      "timestamp_s": 28255,
      "time_str": "14:50",
      "activity_type": "order_failed_timeout",
      "description": "runner_1 received expired order 026; discarding",
      "order_id": "026",
      "location": "clubhouse",
      "runner_id": "runner_1"
    },
    {
      "timestamp_s": 28260,
      "time_str": "14:51",
      "activity_type": "order_assigned",
      "description": "Assigned Order 027 to runner_1",
      "order_id": "027",
      "location": "clubhouse",
      "runner_id": "runner_1"
    },
    {
      "timestamp_s": 28260,
      "time_str": "14:51",
      "activity_type": "order_failed_timeout",
      "description": "runner_1 received expired order 027; discarding",
      "order_id": "027",
      "location": "clubhouse",
      "runner_id": "runner_1"
    },
    {
      "timestamp_s": 28265,
      "time_str": "14:51",
      "activity_type": "order_assigned",
      "description": "Assigned Order 028 to runner_1",
      "order_id": "028",
      "location": "clubhouse",
      "runner_id": "runner_1"
    },
    {
      "timestamp_s": 28265,
      "time_str": "14:51",
      "activity_type": "order_failed_timeout",
      "description": "runner_1 received expired order 028; discarding",
      "order_id": "028",
      "location": "clubhouse",
      "runner_id": "runner_1"
    },
    {
      "timestamp_s": 28270,
      "time_str": "14:51",
      "activity_type": "order_assigned",
      "description": "Assigned Order 029 to runner_1",
      "order_id": "029",
      "location": "clubhouse",
      "runner_id": "runner_1"
    },
    {
      "timestamp_s": 28270,
      "time_str": "14:51",
      "activity_type": "prep_start",
      "description": "runner_1 started prep for Order 029 (Hole 18)",
      "order_id": "029",
      "location": "clubhouse",
      "runner_id": "runner_1"
    },
    {
      "timestamp_s": 28870,
      "time_str": "15:01",
      "activity_type": "prep_complete",
      "description": "runner_1 completed prep for Order 029",
      "order_id": "029",
      "location": "clubhouse",
      "runner_id": "runner_1"
    },
    {
      "timestamp_s": 28870,
      "time_str": "15:01",
      "activity_type": "order_failed_timeout",
      "description": "runner_1 exceeded timeout before departure for Order 029; discarding",
      "order_id": "029",
      "location": "clubhouse",
      "runner_id": "runner_1"
    },
    {
      "timestamp_s": 28870,
      "time_str": "15:01",
      "activity_type": "order_assigned",
      "description": "Assigned Order 030 to runner_1",
      "order_id": "030",
      "location": "clubhouse",
      "runner_id": "runner_1"
    },
    {
      "timestamp_s": 28870,
      "time_str": "15:01",
      "activity_type": "prep_start",
      "description": "runner_1 started prep for Order 030 (Hole 17)",
      "order_id": "030",
      "location": "clubhouse",
      "runner_id": "runner_1"
    },
    {
      "timestamp_s": 29470,
      "time_str": "15:11",
      "activity_type": "prep_complete",
      "description": "runner_1 completed prep for Order 030",
      "order_id": "030",
      "location": "clubhouse",
      "runner_id": "runner_1"
    },
    {
      "timestamp_s": 29470,
      "time_str": "15:11",
      "activity_type": "delivery_start",
      "description": "runner_1 departing to Hole 18 (113m, 0.3 min)",
      "order_id": "030",
      "location": "clubhouse",
      "runner_id": "runner_1"
    },
    {
      "timestamp_s": 29490.180150702276,
      "time_str": "15:11",
      "activity_type": "delivery_complete",
      "description": "runner_1 delivered Order 030 to Hole 18 (Total completion: 58.3 min)",
      "order_id": "030",
      "location": "hole_18",
      "runner_id": "runner_1"
    },
    {
      "timestamp_s": 29490.180150702276,
      "time_str": "15:11",
      "activity_type": "returning",
      "description": "runner_1 returning to clubhouse from hole_18 (1.2 min)",
      "order_id": "030",
      "location": "hole_18",
      "runner_id": "runner_1"
    },
    {
      "timestamp_s": 29561.608722130848,
      "time_str": "15:12",
      "activity_type": "arrived_clubhouse",
      "description": "runner_1 arrived at clubhouse after delivering Order 030",
      "order_id": "030",
      "location": "clubhouse",
      "runner_id": "runner_1"
    },
    {
      "timestamp_s": 29565,
      "time_str": "15:12",
      "activity_type": "order_assigned",
      "description": "Assigned Order 031 to runner_1",
      "order_id": "031",
      "location": "clubhouse",
      "runner_id": "runner_1"
    },
    {
      "timestamp_s": 29565,
      "time_str": "15:12",
      "activity_type": "prep_start",
      "description": "runner_1 started prep for Order 031 (Hole 11)",
      "order_id": "031",
      "location": "clubhouse",
      "runner_id": "runner_1"
    },
    {
      "timestamp_s": 30165,
      "time_str": "15:22",
      "activity_type": "prep_complete",
      "description": "runner_1 completed prep for Order 031",
      "order_id": "031",
      "location": "clubhouse",
      "runner_id": "runner_1"
    },
    {
      "timestamp_s": 30165,
      "time_str": "15:22",
      "activity_type": "order_failed_timeout",
      "description": "runner_1 exceeded timeout before departure for Order 031; discarding",
      "order_id": "031",
      "location": "clubhouse",
      "runner_id": "runner_1"
    },
    {
      "timestamp_s": 30165,
      "time_str": "15:22",
      "activity_type": "order_assigned",
      "description": "Assigned Order 032 to runner_1",
      "order_id": "032",
      "location": "clubhouse",
      "runner_id": "runner_1"
    },
    {
      "timestamp_s": 30165,
      "time_str": "15:22",
      "activity_type": "order_failed_timeout",
      "description": "runner_1 received expired order 032; discarding",
      "order_id": "032",
      "location": "clubhouse",
      "runner_id": "runner_1"
    },
    {
      "timestamp_s": 30170,
      "time_str": "15:22",
      "activity_type": "order_assigned",
      "description": "Assigned Order 033 to runner_1",
      "order_id": "033",
      "location": "clubhouse",
      "runner_id": "runner_1"
    },
    {
      "timestamp_s": 30170,
      "time_str": "15:22",
      "activity_type": "prep_start",
      "description": "runner_1 started prep for Order 033 (Hole 8)",
      "order_id": "033",
      "location": "clubhouse",
      "runner_id": "runner_1"
    },
    {
      "timestamp_s": 30770,
      "time_str": "15:32",
      "activity_type": "prep_complete",
      "description": "runner_1 completed prep for Order 033",
      "order_id": "033",
      "location": "clubhouse",
      "runner_id": "runner_1"
    },
    {
      "timestamp_s": 30770,
      "time_str": "15:32",
      "activity_type": "delivery_start",
      "description": "runner_1 departing to Hole 14 (2467m, 7.3 min)",
      "order_id": "033",
      "location": "clubhouse",
      "runner_id": "runner_1"
    },
    {
      "timestamp_s": 31210.576207777147,
      "time_str": "15:40",
      "activity_type": "delivery_complete",
      "description": "runner_1 delivered Order 033 to Hole 14 (Total completion: 63.5 min)",
      "order_id": "033",
      "location": "hole_14",
      "runner_id": "runner_1"
    },
    {
      "timestamp_s": 31210.576207777147,
      "time_str": "15:40",
      "activity_type": "returning",
      "description": "runner_1 returning to clubhouse from hole_14 (6.0 min)",
      "order_id": "033",
      "location": "hole_14",
      "runner_id": "runner_1"
    },
    {
      "timestamp_s": 31567.719064920006,
      "time_str": "15:46",
      "activity_type": "arrived_clubhouse",
      "description": "runner_1 arrived at clubhouse after delivering Order 033",
      "order_id": "033",
      "location": "clubhouse",
      "runner_id": "runner_1"
    },
    {
      "timestamp_s": 31570,
      "time_str": "15:46",
      "activity_type": "order_assigned",
      "description": "Assigned Order 034 to runner_1",
      "order_id": "034",
      "location": "clubhouse",
      "runner_id": "runner_1"
    },
    {
      "timestamp_s": 31570,
      "time_str": "15:46",
      "activity_type": "prep_start",
      "description": "runner_1 started prep for Order 034 (Hole 12)",
      "order_id": "034",
      "location": "clubhouse",
      "runner_id": "runner_1"
    },
    {
      "timestamp_s": 32170,
      "time_str": "15:56",
      "activity_type": "prep_complete",
      "description": "runner_1 completed prep for Order 034",
      "order_id": "034",
      "location": "clubhouse",
      "runner_id": "runner_1"
    },
    {
      "timestamp_s": 32170,
      "time_str": "15:56",
      "activity_type": "order_failed_timeout",
      "description": "runner_1 exceeded timeout before departure for Order 034; discarding",
      "order_id": "034",
      "location": "clubhouse",
      "runner_id": "runner_1"
    },
    {
      "timestamp_s": 32170,
      "time_str": "15:56",
      "activity_type": "order_assigned",
      "description": "Assigned Order 035 to runner_1",
      "order_id": "035",
      "location": "clubhouse",
      "runner_id": "runner_1"
    },
    {
      "timestamp_s": 32170,
      "time_str": "15:56",
      "activity_type": "prep_start",
      "description": "runner_1 started prep for Order 035 (Hole 8)",
      "order_id": "035",
      "location": "clubhouse",
      "runner_id": "runner_1"
    },
    {
      "timestamp_s": 32770,
      "time_str": "16:06",
      "activity_type": "prep_complete",
      "description": "runner_1 completed prep for Order 035",
      "order_id": "035",
      "location": "clubhouse",
      "runner_id": "runner_1"
    },
    {
      "timestamp_s": 32770,
      "time_str": "16:06",
      "activity_type": "order_failed_timeout",
      "description": "runner_1 exceeded timeout before departure for Order 035; discarding",
      "order_id": "035",
      "location": "clubhouse",
      "runner_id": "runner_1"
    },
    {
      "timestamp_s": 32770,
      "time_str": "16:06",
      "activity_type": "order_assigned",
      "description": "Assigned Order 036 to runner_1",
      "order_id": "036",
      "location": "clubhouse",
      "runner_id": "runner_1"
    },
    {
      "timestamp_s": 32770,
      "time_str": "16:06",
      "activity_type": "prep_start",
      "description": "runner_1 started prep for Order 036 (Hole 18)",
      "order_id": "036",
      "location": "clubhouse",
      "runner_id": "runner_1"
    },
    {
      "timestamp_s": 33370,
      "time_str": "16:16",
      "activity_type": "prep_complete",
      "description": "runner_1 completed prep for Order 036",
      "order_id": "036",
      "location": "clubhouse",
      "runner_id": "runner_1"
    },
    {
      "timestamp_s": 33370,
      "time_str": "16:16",
      "activity_type": "delivery_start",
      "description": "runner_1 departing to Hole 18 (113m, 0.3 min)",
      "order_id": "036",
      "location": "clubhouse",
      "runner_id": "runner_1"
    },
    {
      "timestamp_s": 33390.180150702276,
      "time_str": "16:16",
      "activity_type": "delivery_complete",
      "description": "runner_1 delivered Order 036 to Hole 18 (Total completion: 48.3 min)",
      "order_id": "036",
      "location": "hole_18",
      "runner_id": "runner_1"
    },
    {
      "timestamp_s": 33390.180150702276,
      "time_str": "16:16",
      "activity_type": "returning",
      "description": "runner_1 returning to clubhouse from hole_18 (1.2 min)",
      "order_id": "036",
      "location": "hole_18",
      "runner_id": "runner_1"
    },
    {
      "timestamp_s": 33461.60872213085,
      "time_str": "16:17",
      "activity_type": "arrived_clubhouse",
      "description": "runner_1 arrived at clubhouse after delivering Order 036",
      "order_id": "036",
      "location": "clubhouse",
      "runner_id": "runner_1"
    },
    {
      "timestamp_s": 33465,
      "time_str": "16:17",
      "activity_type": "order_assigned",
      "description": "Assigned Order 037 to runner_1",
      "order_id": "037",
      "location": "clubhouse",
      "runner_id": "runner_1"
    },
    {
      "timestamp_s": 33465,
      "time_str": "16:17",
      "activity_type": "prep_start",
      "description": "runner_1 started prep for Order 037 (Hole 18)",
      "order_id": "037",
      "location": "clubhouse",
      "runner_id": "runner_1"
    },
    {
      "timestamp_s": 34065,
      "time_str": "16:27",
      "activity_type": "prep_complete",
      "description": "runner_1 completed prep for Order 037",
      "order_id": "037",
      "location": "clubhouse",
      "runner_id": "runner_1"
    },
    {
      "timestamp_s": 34065,
      "time_str": "16:27",
      "activity_type": "delivery_start",
      "description": "runner_1 departing to Hole 18 (113m, 0.3 min)",
      "order_id": "037",
      "location": "clubhouse",
      "runner_id": "runner_1"
    },
    {
      "timestamp_s": 34085.180150702276,
      "time_str": "16:28",
      "activity_type": "delivery_complete",
      "description": "runner_1 delivered Order 037 to Hole 18 (Total completion: 50.2 min)",
      "order_id": "037",
      "location": "hole_18",
      "runner_id": "runner_1"
    },
    {
      "timestamp_s": 34085.180150702276,
      "time_str": "16:28",
      "activity_type": "returning",
      "description": "runner_1 returning to clubhouse from hole_18 (1.2 min)",
      "order_id": "037",
      "location": "hole_18",
      "runner_id": "runner_1"
    },
    {
      "timestamp_s": 34156.60872213085,
      "time_str": "16:29",
      "activity_type": "arrived_clubhouse",
      "description": "runner_1 arrived at clubhouse after delivering Order 037",
      "order_id": "037",
      "location": "clubhouse",
      "runner_id": "runner_1"
    },
    {
      "timestamp_s": 34160,
      "time_str": "16:29",
      "activity_type": "order_assigned",
      "description": "Assigned Order 038 to runner_1",
      "order_id": "038",
      "location": "clubhouse",
      "runner_id": "runner_1"
    },
    {
      "timestamp_s": 34160,
      "time_str": "16:29",
      "activity_type": "prep_start",
      "description": "runner_1 started prep for Order 038 (Hole 14)",
      "order_id": "038",
      "location": "clubhouse",
      "runner_id": "runner_1"
    },
    {
      "timestamp_s": 34760,
      "time_str": "16:39",
      "activity_type": "prep_complete",
      "description": "runner_1 completed prep for Order 038",
      "order_id": "038",
      "location": "clubhouse",
      "runner_id": "runner_1"
    },
    {
      "timestamp_s": 34760,
      "time_str": "16:39",
      "activity_type": "delivery_start",
      "description": "runner_1 departing to Hole 17 (1645m, 4.9 min)",
      "order_id": "038",
      "location": "clubhouse",
      "runner_id": "runner_1"
    },
    {
      "timestamp_s": 35053.72536193569,
      "time_str": "16:44",
      "activity_type": "delivery_complete",
      "description": "runner_1 delivered Order 038 to Hole 17 (Total completion: 33.6 min)",
      "order_id": "038",
      "location": "hole_17",
      "runner_id": "runner_1"
    },
    {
      "timestamp_s": 35053.72536193569,
      "time_str": "16:44",
      "activity_type": "returning",
      "description": "runner_1 returning to clubhouse from hole_17 (2.4 min)",
      "order_id": "038",
      "location": "hole_17",
      "runner_id": "runner_1"
    },
    {
      "timestamp_s": 35196.58250479284,
      "time_str": "16:46",
      "activity_type": "arrived_clubhouse",
      "description": "runner_1 arrived at clubhouse after delivering Order 038",
      "order_id": "038",
      "location": "clubhouse",
      "runner_id": "runner_1"
    },
    {
      "timestamp_s": 35200,
      "time_str": "16:46",
      "activity_type": "order_assigned",
      "description": "Assigned Order 039 to runner_1",
      "order_id": "039",
      "location": "clubhouse",
      "runner_id": "runner_1"
    },
    {
      "timestamp_s": 35200,
      "time_str": "16:46",
      "activity_type": "prep_start",
      "description": "runner_1 started prep for Order 039 (Hole 7)",
      "order_id": "039",
      "location": "clubhouse",
      "runner_id": "runner_1"
    },
    {
      "timestamp_s": 35800,
      "time_str": "16:56",
      "activity_type": "prep_complete",
      "description": "runner_1 completed prep for Order 039",
      "order_id": "039",
      "location": "clubhouse",
      "runner_id": "runner_1"
    },
    {
      "timestamp_s": 35800,
      "time_str": "16:56",
      "activity_type": "delivery_start",
      "description": "runner_1 departing to Hole 12 (1232m, 3.7 min)",
      "order_id": "039",
      "location": "clubhouse",
      "runner_id": "runner_1"
    },
    {
      "timestamp_s": 36020.07264143461,
      "time_str": "17:00",
      "activity_type": "delivery_complete",
      "description": "runner_1 delivered Order 039 to Hole 12 (Total completion: 46.4 min)",
      "order_id": "039",
      "location": "hole_12",
      "runner_id": "runner_1"
    },
    {
      "timestamp_s": 36020.07264143461,
      "time_str": "17:00",
      "activity_type": "returning",
      "description": "runner_1 returning to clubhouse from hole_12 (8.3 min)",
      "order_id": "039",
      "location": "hole_12",
      "runner_id": "runner_1"
    },
    {
      "timestamp_s": 36520.07264143461,
      "time_str": "17:08",
      "activity_type": "arrived_clubhouse",
      "description": "runner_1 arrived at clubhouse after delivering Order 039",
      "order_id": "039",
      "location": "clubhouse",
      "runner_id": "runner_1"
    },
    {
      "timestamp_s": 36525,
      "time_str": "17:08",
      "activity_type": "order_assigned",
      "description": "Assigned Order 040 to runner_1",
      "order_id": "040",
      "location": "clubhouse",
      "runner_id": "runner_1"
    },
    {
      "timestamp_s": 36525,
      "time_str": "17:08",
      "activity_type": "prep_start",
      "description": "runner_1 started prep for Order 040 (Hole 17)",
      "order_id": "040",
      "location": "clubhouse",
      "runner_id": "runner_1"
    },
    {
      "timestamp_s": 37125,
      "time_str": "17:18",
      "activity_type": "prep_complete",
      "description": "runner_1 completed prep for Order 040",
      "order_id": "040",
      "location": "clubhouse",
      "runner_id": "runner_1"
    },
    {
      "timestamp_s": 37125,
      "time_str": "17:18",
      "activity_type": "order_failed_timeout",
      "description": "runner_1 exceeded timeout before departure for Order 040; discarding",
      "order_id": "040",
      "location": "clubhouse",
      "runner_id": "runner_1"
    },
    {
      "timestamp_s": 37125,
      "time_str": "17:18",
      "activity_type": "order_assigned",
      "description": "Assigned Order 041 to runner_1",
      "order_id": "041",
      "location": "clubhouse",
      "runner_id": "runner_1"
    },
    {
      "timestamp_s": 37125,
      "time_str": "17:18",
      "activity_type": "prep_start",
      "description": "runner_1 started prep for Order 041 (Hole 14)",
      "order_id": "041",
      "location": "clubhouse",
      "runner_id": "runner_1"
    },
    {
      "timestamp_s": 37725,
      "time_str": "17:28",
      "activity_type": "prep_complete",
      "description": "runner_1 completed prep for Order 041",
      "order_id": "041",
      "location": "clubhouse",
      "runner_id": "runner_1"
    },
    {
      "timestamp_s": 37725,
      "time_str": "17:28",
      "activity_type": "order_failed_timeout",
      "description": "runner_1 exceeded timeout before departure for Order 041; discarding",
      "order_id": "041",
      "location": "clubhouse",
      "runner_id": "runner_1"
    },
    {
      "timestamp_s": 37725,
      "time_str": "17:28",
      "activity_type": "order_assigned",
      "description": "Assigned Order 042 to runner_1",
      "order_id": "042",
      "location": "clubhouse",
      "runner_id": "runner_1"
    },
    {
      "timestamp_s": 37725,
      "time_str": "17:28",
      "activity_type": "prep_start",
      "description": "runner_1 started prep for Order 042 (Hole 9)",
      "order_id": "042",
      "location": "clubhouse",
      "runner_id": "runner_1"
    },
    {
      "timestamp_s": 38325,
      "time_str": "17:38",
      "activity_type": "prep_complete",
      "description": "runner_1 completed prep for Order 042",
      "order_id": "042",
      "location": "clubhouse",
      "runner_id": "runner_1"
    },
    {
      "timestamp_s": 38325,
      "time_str": "17:38",
      "activity_type": "delivery_start",
      "description": "runner_1 departing to Hole 14 (2467m, 7.3 min)",
      "order_id": "042",
      "location": "clubhouse",
      "runner_id": "runner_1"
    },
    {
      "timestamp_s": 38765.57620777715,
      "time_str": "17:46",
      "activity_type": "delivery_complete",
      "description": "runner_1 delivered Order 042 to Hole 14 (Total completion: 51.9 min)",
      "order_id": "042",
      "location": "hole_14",
      "runner_id": "runner_1"
    },
    {
      "timestamp_s": 38765.57620777715,
      "time_str": "17:46",
      "activity_type": "returning",
      "description": "runner_1 returning to clubhouse from hole_14 (6.0 min)",
      "order_id": "042",
      "location": "hole_14",
      "runner_id": "runner_1"
    },
    {
      "timestamp_s": 39122.719064920006,
      "time_str": "17:52",
      "activity_type": "arrived_clubhouse",
      "description": "runner_1 arrived at clubhouse after delivering Order 042",
      "order_id": "042",
      "location": "clubhouse",
      "runner_id": "runner_1"
    },
    {
      "timestamp_s": 39125,
      "time_str": "17:52",
      "activity_type": "order_assigned",
      "description": "Assigned Order 043 to runner_1",
      "order_id": "043",
      "location": "clubhouse",
      "runner_id": "runner_1"
    },
    {
      "timestamp_s": 39125,
      "time_str": "17:52",
      "activity_type": "prep_start",
      "description": "runner_1 started prep for Order 043 (Hole 7)",
      "order_id": "043",
      "location": "clubhouse",
      "runner_id": "runner_1"
    },
    {
      "timestamp_s": 39725,
      "time_str": "18:02",
      "activity_type": "prep_complete",
      "description": "runner_1 completed prep for Order 043",
      "order_id": "043",
      "location": "clubhouse",
      "runner_id": "runner_1"
    },
    {
      "timestamp_s": 39725,
      "time_str": "18:02",
      "activity_type": "order_failed_timeout",
      "description": "runner_1 exceeded timeout before departure for Order 043; discarding",
      "order_id": "043",
      "location": "clubhouse",
      "runner_id": "runner_1"
    },
    {
      "timestamp_s": 39725,
      "time_str": "18:02",
      "activity_type": "service_closed",
      "description": "runner_1 shift ended",
      "order_id": null,
      "location": "clubhouse",
      "runner_id": "runner_1"
    },
    {
      "timestamp_s": 39725,
      "time_str": "18:02",
      "activity_type": "order_assigned",
      "description": "Assigned Order 044 to runner_1",
      "order_id": "044",
      "location": "clubhouse",
      "runner_id": "runner_1"
    }
  ],
  "metadata": {
    "prep_time_min": 10,
    "runner_speed_mps": 2.8,
    "num_groups": 68,
    "num_runners": 1,
    "course_dir": "C:\\Main\\GIT\\simulation\\courses\\keswick_hall",
    "service_open_s": 14400,
    "service_close_s": 39600,
    "blocked_holes": [
      1,
      2,
      3,
      4,
      5,
      6
    ],
    "variant_key": "front_mid"
  }
}