{
  "simulation_id": "delivery_dynamic_02",
  "runner_id": "3_runners",
  "revenue_per_round": 40.0,
  "orders_per_runner_hour": 2.7612863559683003,
  "on_time_rate": 1.0,
  "delivery_cycle_time_p90": 17.492863863486686,
  "delivery_cycle_time_avg": 14.472987856183018,
  "failed_rate": 0.0,
  "second_runner_break_even_orders": 7.243001058825934,
  "queue_wait_avg": 0.03333333333333333,
  "runner_utilization_driving_pct": 56.08977854142188,
  "runner_utilization_prep_pct": 0.0,
  "runner_utilization_idle_pct": 43.91022145857812,
  "distance_per_delivery_avg": 1495.0839196774941,
  "zone_service_times": {
    "hole_13": 16.396904441898066,
    "hole_14": 14.92613011036001,
    "hole_11": 14.888449456747125,
    "hole_-1": 10.597355997261749,
    "hole_18": 11.855187343422585,
    "hole_10": 12.485257282009359,
    "hole_12": 17.244505204105007,
    "hole_7": 15.844340563116475,
    "hole_17": 14.284642161329975,
    "hole_9": 13.05753822313133,
    "hole_6": 19.16309706856506
  },
  "total_revenue": 600.0,
  "total_orders": 20,
  "successful_orders": 20,
  "failed_orders": 0,
  "total_rounds": 15,
  "active_runner_hours": 7.243001058825933
}